[{"id":1,"asset_code":"5GR22AYARBILEZIK","buy_price":35040.75,"sell_price":36741.35,"updated_at":"2026-01-28T20:30:27.895+00:00","name":"5 Gr 22 Ayar Bilezik","category":"22AYAR","category_display_name":"22 Ayar","live_data":false,"icon_path":"icons/ring.png","ui_color":"text-amber-500","ui_bg":"bg-amber-500/20","prefix":"Adet"},{"id":2,"asset_code":"7GR22AYARBILEZIK","buy_price":49057.05,"sell_price":51437.89,"updated_at":"2026-01-28T20:30:27.895+00:00","name":"7 Gr 22 Ayar Bilezik","category":"22AYAR","category_display_name":"22 Ayar","live_data":false,"icon_path":"icons/ring.png","ui_color":"text-amber-500","ui_bg":"bg-amber-500/20","prefix":"Adet"},{"id":3,"asset_code":"10GR22AYARBILEZIK","buy_price":70081.5,"sell_price":73482.7,"updated_at":"2026-01-28T20:30:27.895+00:00","name":"10 Gr 22 Ayar Bilezik","category":"22AYAR","category_display_name":"22 Ayar","live_data":false,"icon_path":"icons/ring.png","ui_color":"text-amber-500","ui_bg":"bg-amber-500/20","prefix":"Adet"},{"id":4,"asset_code":"15GR22AYARBILEZIK","buy_price":105122.25,"sell_price":110224.05,"updated_at":"2026-01-28T20:30:27.895+00:00","name":"15 Gr 22 Ayar Bilezik","category":"22AYAR","category_display_name":"22 Ayar","live_data":false,"icon_path":"icons/ring.png","ui_color":"text-amber-500","ui_bg":"bg-amber-500/20","prefix":"Adet"},{"id":5,"asset_code":"20GR22AYARBILEZIK","buy_price":140163,"sell_price":146965.4,"updated_at":"2026-01-28T20:30:27.895+00:00","name":"20 Gr 22 Ayar Bilezik","category":"22AYAR","category_display_name":"22 Ayar","live_data":false,"icon_path":"icons/ring.png","ui_color":"text-amber-500","ui_bg":"bg-amber-500/20","prefix":"Adet"},{"id":6,"asset_code":"25GR22AYARBILEZIK","buy_price":175203.75,"sell_price":183706.75,"updated_at":"2026-01-28T20:30:27.895+00:00","name":"25 Gr 22 Ayar Bilezik","category":"22AYAR","category_display_name":"22 Ayar","live_data":false,"icon_path":"icons/ring.png","ui_color":"text-amber-500","ui_bg":"bg-amber-500/20","prefix":"Adet"},{"id":7,"asset_code":"30GR22AYARBILEZIK","buy_price":210244.5,"sell_price":220448.1,"updated_at":"2026-01-28T20:30:27.895+00:00","name":"30 Gr 22 Ayar Bilezik","category":"22AYAR","category_display_name":"22 Ayar","live_data":false,"icon_path":"icons/ring.png","ui_color":"text-amber-500","ui_bg":"bg-amber-500/20","prefix":"Adet"},{"id":8,"asset_code":"5GR14AYARBILEZIK","buy_price":21269.7,"sell_price":27707.25,"updated_at":"2026-01-28T20:30:27.895+00:00","name":"5 Gr 14 Ayar Bilezik","category":"14AYAR","category_display_name":"14 Ayar","live_data":false,"icon_path":"icons/ring.png","ui_color":"text-amber-500","ui_bg":"bg-amber-500/20","prefix":"Adet"},{"id":9,"asset_code":"7GR14AYARBILEZIK","buy_price":29777.58,"sell_price":38790.15,"updated_at":"2026-01-28T20:30:27.895+00:00","name":"7 Gr 14 Ayar Bilezik","category":"14AYAR","category_display_name":"14 Ayar","live_data":false,"icon_path":"icons/ring.png","ui_color":"text-amber-500","ui_bg":"bg-amber-500/20","prefix":"Adet"},{"id":10,"asset_code":"10GR14AYARBILEZIK","buy_price":42539.4,"sell_price":55414.5,"updated_at":"2026-01-28T20:30:27.895+00:00","name":"10 Gr 14 Ayar Bilezik","category":"14AYAR","category_display_name":"14 Ayar","live_data":false,"icon_path":"icons/ring.png","ui_color":"text-amber-500","ui_bg":"bg-amber-500/20","prefix":"Adet"},{"id":14,"asset_code":"15GR14AYARBILEZIK","buy_price":63809.1,"sell_price":83121.75,"updated_at":"2026-01-28T20:30:27.895+00:00","name":"15 Gr 14 Ayar Bilezik","category":"14AYAR","category_display_name":"14 Ayar","live_data":false,"icon_path":"icons/ring.png","ui_color":"text-amber-500","ui_bg":"bg-amber-500/20","prefix":"Adet"},{"id":15,"asset_code":"20GR14AYARBILEZIK","buy_price":85078.8,"sell_price":110829,"updated_at":"2026-01-28T20:30:27.895+00:00","name":"20 Gr 14 Ayar Bilezik","category":"14AYAR","category_display_name":"14 Ayar","live_data":false,"icon_path":"icons/ring.png","ui_color":"text-amber-500","ui_bg":"bg-amber-500/20","prefix":"Adet"},{"id":16,"asset_code":"25GR14AYARBILEZIK","buy_price":106348.5,"sell_price":138536.25,"updated_at":"2026-01-28T20:30:27.895+00:00","name":"25 Gr 14 Ayar Bilezik","category":"14AYAR","category_display_name":"14 Ayar","live_data":false,"icon_path":"icons/ring.png","ui_color":"text-amber-500","ui_bg":"bg-amber-500/20","prefix":"Adet"},{"id":17,"asset_code":"30GR14AYARBILEZIK","buy_price":127618.2,"sell_price":166243.5,"updated_at":"2026-01-28T20:30:27.896+00:00","name":"30 Gr 14 Ayar Bilezik","category":"14AYAR","category_display_name":"14 Ayar","live_data":false,"icon_path":"icons/ring.png","ui_color":"text-amber-500","ui_bg":"bg-amber-500/20","prefix":"Adet"},{"id":18,"asset_code":"2.5GRKULCEALTIN","buy_price":19219.83,"sell_price":19506.7,"updated_at":"2026-01-28T20:30:27.896+00:00","name":"2.5 Gram Külçe Altın","category":"KULCEALTIN","category_display_name":"Külçe Altın","live_data":false,"icon_path":"icons/gold.png","ui_color":"text-amber-500","ui_bg":"bg-amber-500/20","prefix":"Adet"},{"id":19,"asset_code":"5GRKULCEALTIN","buy_price":38439.65,"sell_price":39013.4,"updated_at":"2026-01-28T20:30:27.896+00:00","name":"5 Gram Külçe Altın","category":"KULCEALTIN","category_display_name":"Külçe Altın","live_data":false,"icon_path":"icons/gold.png","ui_color":"text-amber-500","ui_bg":"bg-amber-500/20","prefix":"Adet"},{"id":20,"asset_code":"10GRKULCEALTIN","buy_price":76879.3,"sell_price":78026.8,"updated_at":"2026-01-28T20:30:27.896+00:00","name":"10 Gram Külçe Altın","category":"KULCEALTIN","category_display_name":"Külçe Altın","live_data":false,"icon_path":"icons/gold.png","ui_color":"text-amber-500","ui_bg":"bg-amber-500/20","prefix":"Adet"},{"id":21,"asset_code":"15GRKULCEALTIN","buy_price":115318.95,"sell_price":117040.2,"updated_at":"2026-01-28T20:30:27.896+00:00","name":"15 Gram Külçe Altın","category":"KULCEALTIN","category_display_name":"Külçe Altın","live_data":false,"icon_path":"icons/gold.png","ui_color":"text-amber-500","ui_bg":"bg-amber-500/20","prefix":"Adet"},{"id":22,"asset_code":"20GRKULCEALTIN","buy_price":153758.6,"sell_price":156053.6,"updated_at":"2026-01-28T20:30:27.896+00:00","name":"20 Gram Külçe Altın","category":"KULCEALTIN","category_display_name":"Külçe Altın","live_data":false,"icon_path":"icons/gold.png","ui_color":"text-amber-500","ui_bg":"bg-amber-500/20","prefix":"Adet"},{"id":23,"asset_code":"25GRKULCEALTIN","buy_price":192198.25,"sell_price":195067,"updated_at":"2026-01-28T20:30:27.896+00:00","name":"25 Gram Külçe Altın","category":"KULCEALTIN","category_display_name":"Külçe Altın","live_data":false,"icon_path":"icons/gold.png","ui_color":"text-amber-500","ui_bg":"bg-amber-500/20","prefix":"Adet"},{"id":24,"asset_code":"50GRKULCEALTIN","buy_price":384396.5,"sell_price":390134,"updated_at":"2026-01-28T20:30:27.896+00:00","name":"50 Gram Külçe Altın","category":"KULCEALTIN","category_display_name":"Külçe Altın","live_data":false,"icon_path":"icons/gold.png","ui_color":"text-amber-500","ui_bg":"bg-amber-500/20","prefix":"Adet"},{"id":25,"asset_code":"100GRKULCEALTIN","buy_price":768793,"sell_price":780268,"updated_at":"2026-01-28T20:30:27.896+00:00","name":"100 Gram Külçe Altın","category":"KULCEALTIN","category_display_name":"Külçe Altın","live_data":false,"icon_path":"icons/gold.png","ui_color":"text-amber-500","ui_bg":"bg-amber-500/20","prefix":"Adet"},{"id":26,"asset_code":"200GRKULCEALTIN","buy_price":1537586,"sell_price":1560536,"updated_at":"2026-01-28T20:30:27.896+00:00","name":"200 Gram Külçe Altın","category":"KULCEALTIN","category_display_name":"Külçe Altın","live_data":false,"icon_path":"icons/gold.png","ui_color":"text-amber-500","ui_bg":"bg-amber-500/20","prefix":"Adet"},{"id":27,"asset_code":"250GRKULCEALTIN","buy_price":1921982.5,"sell_price":1950670,"updated_at":"2026-01-28T20:30:27.896+00:00","name":"250 Gram Külçe Altın","category":"KULCEALTIN","category_display_name":"Külçe Altın","live_data":false,"icon_path":"icons/gold.png","ui_color":"text-amber-500","ui_bg":"bg-amber-500/20","prefix":"Adet"},{"id":28,"asset_code":"500GRKULCEALTIN","buy_price":3843965,"sell_price":3901340,"updated_at":"2026-01-28T20:30:27.896+00:00","name":"500 Gram Külçe Altın","category":"KULCEALTIN","category_display_name":"Külçe Altın","live_data":false,"icon_path":"icons/gold.png","ui_color":"text-amber-500","ui_bg":"bg-amber-500/20","prefix":"Adet"},{"id":29,"asset_code":"1000GRKULCEALTIN","buy_price":7687930,"sell_price":7802680,"updated_at":"2026-01-28T20:30:27.896+00:00","name":"1000 Gram Külçe Altın","category":"KULCEALTIN","category_display_name":"Külçe Altın","live_data":false,"icon_path":"icons/gold.png","ui_color":"text-amber-500","ui_bg":"bg-amber-500/20","prefix":"Adet"},{"id":30,"asset_code":"2.5GRKULCEGUMUS","buy_price":408.92,"sell_price":444.45,"updated_at":"2026-01-28T20:30:27.896+00:00","name":"2.5 Gram Külçe Gümüş","category":"KULCEGUMUS","category_display_name":"Külçe Gümüş","live_data":false,"icon_path":"icons/silver.png","ui_color":"text-slate-400","ui_bg":"bg-slate-400/20","prefix":"Adet"},{"id":31,"asset_code":"5GRKULCEGUMUS","buy_price":817.85,"sell_price":888.9,"updated_at":"2026-01-28T20:30:27.896+00:00","name":"5 Gram Külçe Gümüş","category":"KULCEGUMUS","category_display_name":"Külçe Gümüş","live_data":false,"icon_path":"icons/silver.png","ui_color":"text-slate-400","ui_bg":"bg-slate-400/20","prefix":"Adet"},{"id":32,"asset_code":"10GRKULCEGUMUS","buy_price":1635.7,"sell_price":1777.8,"updated_at":"2026-01-28T20:30:27.896+00:00","name":"10 Gram Külçe Gümüş","category":"KULCEGUMUS","category_display_name":"Külçe Gümüş","live_data":false,"icon_path":"icons/silver.png","ui_color":"text-slate-400","ui_bg":"bg-slate-400/20","prefix":"Adet"},{"id":33,"asset_code":"15GRKULCEGUMUS","buy_price":2453.55,"sell_price":2666.7,"updated_at":"2026-01-28T20:30:27.896+00:00","name":"15 Gram Külçe Gümüş","category":"KULCEGUMUS","category_display_name":"Külçe Gümüş","live_data":false,"icon_path":"icons/silver.png","ui_color":"text-slate-400","ui_bg":"bg-slate-400/20","prefix":"Adet"},{"id":34,"asset_code":"20GRKULCEGUMUS","buy_price":3271.4,"sell_price":3555.6,"updated_at":"2026-01-28T20:30:27.896+00:00","name":"20 Gram Külçe Gümüş","category":"KULCEGUMUS","category_display_name":"Külçe Gümüş","live_data":false,"icon_path":"icons/silver.png","ui_color":"text-slate-400","ui_bg":"bg-slate-400/20","prefix":"Adet"},{"id":35,"asset_code":"25GRKULCEGUMUS","buy_price":4089.25,"sell_price":4444.5,"updated_at":"2026-01-28T20:30:27.896+00:00","name":"25 Gram Külçe Gümüş","category":"KULCEGUMUS","category_display_name":"Külçe Gümüş","live_data":false,"icon_path":"icons/silver.png","ui_color":"text-slate-400","ui_bg":"bg-slate-400/20","prefix":"Adet"},{"id":36,"asset_code":"50GRKULCEGUMUS","buy_price":8178.5,"sell_price":8889,"updated_at":"2026-01-28T20:30:27.896+00:00","name":"50 Gram Külçe Gümüş","category":"KULCEGUMUS","category_display_name":"Külçe Gümüş","live_data":false,"icon_path":"icons/silver.png","ui_color":"text-slate-400","ui_bg":"bg-slate-400/20","prefix":"Adet"},{"id":37,"asset_code":"100GRKULCEGUMUS","buy_price":16357,"sell_price":17778,"updated_at":"2026-01-28T20:30:27.896+00:00","name":"100 Gram Külçe Gümüş","category":"KULCEGUMUS","category_display_name":"Külçe Gümüş","live_data":false,"icon_path":"icons/silver.png","ui_color":"text-slate-400","ui_bg":"bg-slate-400/20","prefix":"Adet"},{"id":38,"asset_code":"200GRKULCEGUMUS","buy_price":32714,"sell_price":35556,"updated_at":"2026-01-28T20:30:27.896+00:00","name":"200 Gram Külçe Gümüş","category":"KULCEGUMUS","category_display_name":"Külçe Gümüş","live_data":false,"icon_path":"icons/silver.png","ui_color":"text-slate-400","ui_bg":"bg-slate-400/20","prefix":"Adet"},{"id":39,"asset_code":"250GRKULCEGUMUS","buy_price":40892.5,"sell_price":44445,"updated_at":"2026-01-28T20:30:27.896+00:00","name":"250 Gram Külçe Gümüş","category":"KULCEGUMUS","category_display_name":"Külçe Gümüş","live_data":false,"icon_path":"icons/silver.png","ui_color":"text-slate-400","ui_bg":"bg-slate-400/20","prefix":"Adet"},{"id":40,"asset_code":"500GRKULCEGUMUS","buy_price":81785,"sell_price":88890,"updated_at":"2026-01-28T20:30:27.896+00:00","name":"500 Gram Külçe Gümüş","category":"KULCEGUMUS","category_display_name":"Külçe Gümüş","live_data":false,"icon_path":"icons/silver.png","ui_color":"text-slate-400","ui_bg":"bg-slate-400/20","prefix":"Adet"},{"id":41,"asset_code":"1000GRKULCEGUMUS","buy_price":163570,"sell_price":177780,"updated_at":"2026-01-28T20:30:27.896+00:00","name":"1000 Gram Külçe Gümüş","category":"KULCEGUMUS","category_display_name":"Külçe Gümüş","live_data":false,"icon_path":"icons/silver.png","ui_color":"text-slate-400","ui_bg":"bg-slate-400/20","prefix":"Adet"},{"id":95,"asset_code":"KRIPTO_BTC","buy_price":3890129,"sell_price":3890130,"updated_at":"2026-01-28T20:30:23.395+00:00","name":"Bitcoin","category":"KRIPTO","category_display_name":"Kripto","live_data":true,"icon_path":"icons/bitcoin.png","ui_color":"text-amber-500","ui_bg":"bg-amber-500/20","prefix":"Adet"},{"id":96,"asset_code":"KRIPTO_ETH","buy_price":131399,"sell_price":131400,"updated_at":"2026-01-28T20:30:23.395+00:00","name":"Ethereum","category":"KRIPTO","category_display_name":"Kripto","live_data":true,"icon_path":"icons/ethereum.png","ui_color":"bg-blue-500","ui_bg":"bg-blue-500/20","prefix":"Adet"},{"id":55,"asset_code":"AKBANK_GA","buy_price":7175.19,"sell_price":7690.56,"updated_at":"2026-01-28T20:30:23.396+00:00","name":"Akbank Gram Altın","category":"BANKAALTIN","category_display_name":"Banka Altın","live_data":true,"icon_path":"icons/gold.png","ui_color":"text-amber-500","ui_bg":"bg-amber-500/20","prefix":"Gram"},{"id":56,"asset_code":"ALBARAKA_GA","buy_price":7210.3,"sell_price":7664.89,"updated_at":"2026-01-28T20:30:23.396+00:00","name":"Albaraka Türk Gram Altın","category":"BANKAALTIN","category_display_name":"Banka Altın","live_data":true,"icon_path":"icons/gold.png","ui_color":"text-amber-500","ui_bg":"bg-amber-500/20","prefix":"Gram"},{"id":57,"asset_code":"ALTERNATIF_GA","buy_price":6967.77,"sell_price":7716.94,"updated_at":"2026-01-28T20:30:23.396+00:00","name":"Alternatif Bank Gram Altın","category":"BANKAALTIN","category_display_name":"Banka Altın","live_data":true,"icon_path":"icons/gold.png","ui_color":"text-amber-500","ui_bg":"bg-amber-500/20","prefix":"Gram"},{"id":58,"asset_code":"ANADOLUBANK_GA","buy_price":7370.34,"sell_price":7481.69,"updated_at":"2026-01-28T20:30:23.396+00:00","name":"Anadolubank Gram Altın","category":"BANKAALTIN","category_display_name":"Banka Altın","live_data":true,"icon_path":"icons/gold.png","ui_color":"text-amber-500","ui_bg":"bg-amber-500/20","prefix":"Gram"},{"id":59,"asset_code":"CEBTETEB_GA","buy_price":6868.88,"sell_price":7974.43,"updated_at":"2026-01-28T20:30:23.396+00:00","name":"CEPTETEB Gram Altın","category":"BANKAALTIN","category_display_name":"Banka Altın","live_data":true,"icon_path":"icons/gold.png","ui_color":"text-amber-500","ui_bg":"bg-amber-500/20","prefix":"Gram"},{"id":60,"asset_code":"DENIZBANK_GA","buy_price":7217.58,"sell_price":7701.42,"updated_at":"2026-01-28T20:30:23.396+00:00","name":"DenizBank Gram Altın","category":"BANKAALTIN","category_display_name":"Banka Altın","live_data":true,"icon_path":"icons/gold.png","ui_color":"text-amber-500","ui_bg":"bg-amber-500/20","prefix":"Gram"},{"id":61,"asset_code":"ENPARA_GA","buy_price":7274.02,"sell_price":7668.01,"updated_at":"2026-01-28T20:30:23.396+00:00","name":"Enpara Gram Altın","category":"BANKAALTIN","category_display_name":"Banka Altın","live_data":true,"icon_path":"icons/gold.png","ui_color":"text-amber-500","ui_bg":"bg-amber-500/20","prefix":"Gram"},{"id":62,"asset_code":"FIBABANKA_GA","buy_price":7433,"sell_price":7489.16,"updated_at":"2026-01-28T20:30:23.396+00:00","name":"Fibabanka Gram Altın","category":"BANKAALTIN","category_display_name":"Banka Altın","live_data":true,"icon_path":"icons/gold.png","ui_color":"text-amber-500","ui_bg":"bg-amber-500/20","prefix":"Gram"},{"id":63,"asset_code":"GARANTI_GA","buy_price":7176.48,"sell_price":7682.28,"updated_at":"2026-01-28T20:30:23.396+00:00","name":"Garanti BBVA Gram Altın","category":"BANKAALTIN","category_display_name":"Banka Altın","live_data":true,"icon_path":"icons/gold.png","ui_color":"text-amber-500","ui_bg":"bg-amber-500/20","prefix":"Gram"},{"id":64,"asset_code":"HALKBANK_GA","buy_price":7123.85,"sell_price":7621.35,"updated_at":"2026-01-28T20:30:23.396+00:00","name":"Halkbank Gram Altın","category":"BANKAALTIN","category_display_name":"Banka Altın","live_data":true,"icon_path":"icons/gold.png","ui_color":"text-amber-500","ui_bg":"bg-amber-500/20","prefix":"Gram"},{"id":65,"asset_code":"HSBC_GA","buy_price":7339.57,"sell_price":7599.61,"updated_at":"2026-01-28T20:30:23.396+00:00","name":"HSBC Gram Altın","category":"BANKAALTIN","category_display_name":"Banka Altın","live_data":true,"icon_path":"icons/gold.png","ui_color":"text-amber-500","ui_bg":"bg-amber-500/20","prefix":"Gram"},{"id":66,"asset_code":"ING_GA","buy_price":7317.07,"sell_price":7620.84,"updated_at":"2026-01-28T20:30:23.396+00:00","name":"ING Bank Gram Altın","category":"BANKAALTIN","category_display_name":"Banka Altın","live_data":true,"icon_path":"icons/gold.png","ui_color":"text-amber-500","ui_bg":"bg-amber-500/20","prefix":"Gram"},{"id":67,"asset_code":"KUVEYTTURK_GA","buy_price":7352.03,"sell_price":7566.79,"updated_at":"2026-01-28T20:30:23.396+00:00","name":"Kuveyt Türk Gram Altın","category":"BANKAALTIN","category_display_name":"Banka Altın","live_data":true,"icon_path":"icons/gold.png","ui_color":"text-amber-500","ui_bg":"bg-amber-500/20","prefix":"Gram"},{"id":68,"asset_code":"QNBFB_GA","buy_price":7158.62,"sell_price":7675.1,"updated_at":"2026-01-28T20:30:23.396+00:00","name":"QNB Finansbank Gram Altın","category":"BANKAALTIN","category_display_name":"Banka Altın","live_data":true,"icon_path":"icons/gold.png","ui_color":"text-amber-500","ui_bg":"bg-amber-500/20","prefix":"Gram"},{"id":69,"asset_code":"SEKERBANK_GA","buy_price":7206.39,"sell_price":7657.85,"updated_at":"2026-01-28T20:30:23.396+00:00","name":"Şekerbank Gram Altın","category":"BANKAALTIN","category_display_name":"Banka Altın","live_data":true,"icon_path":"icons/gold.png","ui_color":"text-amber-500","ui_bg":"bg-amber-500/20","prefix":"Gram"},{"id":70,"asset_code":"TURKIYEFINANS_GA","buy_price":7376.69,"sell_price":7580.16,"updated_at":"2026-01-28T20:30:23.396+00:00","name":"Türkiye Finans Gram Altın","category":"BANKAALTIN","category_display_name":"Banka Altın","live_data":true,"icon_path":"icons/gold.png","ui_color":"text-amber-500","ui_bg":"bg-amber-500/20","prefix":"Gram"},{"id":71,"asset_code":"VAKIFBANK_GA","buy_price":7093.73,"sell_price":7918.73,"updated_at":"2026-01-28T20:30:23.396+00:00","name":"VakıfBank Gram Altın","category":"BANKAALTIN","category_display_name":"Banka Altın","live_data":true,"icon_path":"icons/gold.png","ui_color":"text-amber-500","ui_bg":"bg-amber-500/20","prefix":"Gram"},{"id":72,"asset_code":"VAKIFKATILIM_GA","buy_price":7232.45,"sell_price":7551.14,"updated_at":"2026-01-28T20:30:23.396+00:00","name":"Vakıf Katılım Gram Altın","category":"BANKAALTIN","category_display_name":"Banka Altın","live_data":true,"icon_path":"icons/gold.png","ui_color":"text-amber-500","ui_bg":"bg-amber-500/20","prefix":"Gram"},{"id":73,"asset_code":"YAPIKREDI_GA","buy_price":7292,"sell_price":7592.62,"updated_at":"2026-01-28T20:30:23.396+00:00","name":"Yapı Kredi Gram Altın","category":"BANKAALTIN","category_display_name":"Banka Altın","live_data":true,"icon_path":"icons/gold.png","ui_color":"text-amber-500","ui_bg":"bg-amber-500/20","prefix":"Gram"},{"id":74,"asset_code":"ZIRAAT_GA","buy_price":7074.14,"sell_price":8097.68,"updated_at":"2026-01-28T20:30:23.396+00:00","name":"Ziraat Bankası Gram Altın","category":"BANKAALTIN","category_display_name":"Banka Altın","live_data":true,"icon_path":"icons/gold.png","ui_color":"text-amber-500","ui_bg":"bg-amber-500/20","prefix":"Gram"},{"id":75,"asset_code":"ZIRAATKATILIM_GA","buy_price":6593.91,"sell_price":8314.49,"updated_at":"2026-01-28T20:30:23.396+00:00","name":"Ziraat Katılım Gram Altın","category":"BANKAALTIN","category_display_name":"Banka Altın","live_data":true,"icon_path":"icons/gold.png","ui_color":"text-amber-500","ui_bg":"bg-amber-500/20","prefix":"Gram"},{"id":42,"asset_code":"HAS_GA","buy_price":7687.93,"sell_price":7802.68,"updated_at":"2026-01-28T20:30:23.397+00:00","name":"Gram Külçe Altın","category":"KULCEALTIN","category_display_name":"Külçe Altın","live_data":true,"icon_path":"icons/gold.png","ui_color":"text-amber-500","ui_bg":"bg-amber-500/20","prefix":"Adet"},{"id":43,"asset_code":"CEYREK_YENI","buy_price":12557,"sell_price":12686,"updated_at":"2026-01-28T20:30:23.397+00:00","name":"Çeyrek Altın","category":"ZIYNET","category_display_name":"Ziynet","live_data":true,"icon_path":"icons/ceyrek_yarim_tam_ata.png","ui_color":"text-amber-500","ui_bg":"bg-amber-500/20","prefix":"Adet"},{"id":44,"asset_code":"CEYREK_ESKI","buy_price":12364,"sell_price":12492,"updated_at":"2026-01-28T20:30:23.397+00:00","name":"Çeyrek Altın Eski","category":"ZIYNET","category_display_name":"Ziynet","live_data":true,"icon_path":"icons/ceyrek_yarim_tam_ata.png","ui_color":"text-amber-500","ui_bg":"bg-amber-500/20","prefix":"Adet"},{"id":45,"asset_code":"YARIM_YENI","buy_price":25113,"sell_price":25372,"updated_at":"2026-01-28T20:30:23.397+00:00","name":"Yarım Altın","category":"ZIYNET","category_display_name":"Ziynet","live_data":true,"icon_path":"icons/ceyrek_yarim_tam_ata.png","ui_color":"text-amber-500","ui_bg":"bg-amber-500/20","prefix":"Adet"},{"id":46,"asset_code":"YARIM_ESKI","buy_price":24651,"sell_price":24884,"updated_at":"2026-01-28T20:30:23.397+00:00","name":"Yarım Altın Eski","category":"ZIYNET","category_display_name":"Ziynet","live_data":true,"icon_path":"icons/ceyrek_yarim_tam_ata.png","ui_color":"text-amber-500","ui_bg":"bg-amber-500/20","prefix":"Adet"},{"id":47,"asset_code":"TAM_YENI","buy_price":50073,"sell_price":50551,"updated_at":"2026-01-28T20:30:23.397+00:00","name":"Tam Altın","category":"ZIYNET","category_display_name":"Ziynet","live_data":true,"icon_path":"icons/ceyrek_yarim_tam_ata.png","ui_color":"text-amber-500","ui_bg":"bg-amber-500/20","prefix":"Adet"},{"id":48,"asset_code":"TAM_ESKI","buy_price":49418,"sell_price":49876,"updated_at":"2026-01-28T20:30:23.397+00:00","name":"Tam Altın Eski","category":"ZIYNET","category_display_name":"Ziynet","live_data":true,"icon_path":"icons/ceyrek_yarim_tam_ata.png","ui_color":"text-amber-500","ui_bg":"bg-amber-500/20","prefix":"Adet"},{"id":49,"asset_code":"ATA_YENI","buy_price":51421,"sell_price":51869,"updated_at":"2026-01-28T20:30:23.397+00:00","name":"Ata Altın","category":"ZIYNET","category_display_name":"Ziynet","live_data":true,"icon_path":"icons/ceyrek_yarim_tam_ata.png","ui_color":"text-amber-500","ui_bg":"bg-amber-500/20","prefix":"Adet"},{"id":50,"asset_code":"ATA_ESKI","buy_price":51421,"sell_price":51869,"updated_at":"2026-01-28T20:30:23.397+00:00","name":"Ata Altın Eski","category":"ZIYNET","category_display_name":"Ziynet","live_data":true,"icon_path":"icons/ceyrek_yarim_tam_ata.png","ui_color":"text-amber-500","ui_bg":"bg-amber-500/20","prefix":"Adet"},{"id":51,"asset_code":"AYAR14","buy_price":4253.94,"sell_price":5541.45,"updated_at":"2026-01-28T20:30:23.397+00:00","name":"14 Ayar","category":"14AYAR","category_display_name":"14 Ayar","live_data":true,"icon_path":"icons/ring.png","ui_color":"text-amber-500","ui_bg":"bg-amber-500/20","prefix":"Adet"},{"id":52,"asset_code":"AYAR22","buy_price":7008.15,"sell_price":7348.27,"updated_at":"2026-01-28T20:30:23.397+00:00","name":"22 Ayar","category":"22AYAR","category_display_name":"22 Ayar","live_data":true,"icon_path":"icons/ring.png","ui_color":"text-amber-500","ui_bg":"bg-amber-500/20","prefix":"Adet"},{"id":53,"asset_code":"HAS_GG","buy_price":163.57,"sell_price":177.78,"updated_at":"2026-01-28T20:30:23.397+00:00","name":"Gram Külçe Gümüş","category":"KULCEGUMUS","category_display_name":"Külçe Gümüş","live_data":true,"icon_path":"icons/silver.png","ui_color":"text-slate-400","ui_bg":"bg-slate-400/20","prefix":"Adet"},{"id":77,"asset_code":"ISBANK_GA","buy_price":7181.58,"sell_price":7663.98,"updated_at":"2026-01-28T20:30:27.918+00:00","name":"İş Bankası Gram Altın","category":"BANKAALTIN","category_display_name":"Banka Altın","live_data":true,"icon_path":"icons/gold.png","ui_color":"text-amber-500","ui_bg":"bg-amber-500/20","prefix":"Gram"},{"id":78,"asset_code":"AKBANK_GG","buy_price":155.18,"sell_price":166.39,"updated_at":"2026-01-28T20:30:34.234+00:00","name":"Akbank Gram Gümüş","category":"BANKAGUMUS","category_display_name":"Banka Gümüş","live_data":true,"icon_path":"icons/silver.png","ui_color":"text-slate-400","ui_bg":"bg-slate-400/20","prefix":"Gram"},{"id":79,"asset_code":"ALBARAKA_GG","buy_price":154.54,"sell_price":166.22,"updated_at":"2026-01-28T20:30:34.234+00:00","name":"Albaraka Türk Gram Gümüş","category":"BANKAGUMUS","category_display_name":"Banka Gümüş","live_data":true,"icon_path":"icons/silver.png","ui_color":"text-slate-400","ui_bg":"bg-slate-400/20","prefix":"Gram"},{"id":80,"asset_code":"ANADOLUBANK_GG","buy_price":157.48,"sell_price":163.82,"updated_at":"2026-01-28T20:30:34.234+00:00","name":"Anadolubank Gram Gümüş","category":"BANKAGUMUS","category_display_name":"Banka Gümüş","live_data":true,"icon_path":"icons/silver.png","ui_color":"text-slate-400","ui_bg":"bg-slate-400/20","prefix":"Gram"},{"id":81,"asset_code":"DENIZBANK_GG","buy_price":155.23,"sell_price":165.75,"updated_at":"2026-01-28T20:30:34.234+00:00","name":"DenizBank Gram Gümüş","category":"BANKAGUMUS","category_display_name":"Banka Gümüş","live_data":true,"icon_path":"icons/silver.png","ui_color":"text-slate-400","ui_bg":"bg-slate-400/20","prefix":"Gram"},{"id":82,"asset_code":"FIBABANKA_GG","buy_price":160.35,"sell_price":161.24,"updated_at":"2026-01-28T20:30:34.234+00:00","name":"Fibabanka Gram Gümüş","category":"BANKAGUMUS","category_display_name":"Banka Gümüş","live_data":true,"icon_path":"icons/silver.png","ui_color":"text-slate-400","ui_bg":"bg-slate-400/20","prefix":"Gram"},{"id":83,"asset_code":"GARANTI_GG","buy_price":152.35,"sell_price":166.96,"updated_at":"2026-01-28T20:30:34.234+00:00","name":"Garanti BBVA Gram Gümüş","category":"BANKAGUMUS","category_display_name":"Banka Gümüş","live_data":true,"icon_path":"icons/silver.png","ui_color":"text-slate-400","ui_bg":"bg-slate-400/20","prefix":"Gram"},{"id":84,"asset_code":"HSBC_GG","buy_price":158.59,"sell_price":164.33,"updated_at":"2026-01-28T20:30:34.234+00:00","name":"HSBC Gram Gümüş","category":"BANKAGUMUS","category_display_name":"Banka Gümüş","live_data":true,"icon_path":"icons/silver.png","ui_color":"text-slate-400","ui_bg":"bg-slate-400/20","prefix":"Gram"},{"id":85,"asset_code":"KUVEYTTURK_GG","buy_price":159.06,"sell_price":163.73,"updated_at":"2026-01-28T20:30:34.234+00:00","name":"Kuveyt Türk Gram Gümüş","category":"BANKAGUMUS","category_display_name":"Banka Gümüş","live_data":true,"icon_path":"icons/silver.png","ui_color":"text-slate-400","ui_bg":"bg-slate-400/20","prefix":"Gram"},{"id":86,"asset_code":"TURKIYEFINANS_GG","buy_price":159.63,"sell_price":167.72,"updated_at":"2026-01-28T20:30:34.234+00:00","name":"Türkiye Finans Gram Gümüş","category":"BANKAGUMUS","category_display_name":"Banka Gümüş","live_data":true,"icon_path":"icons/silver.png","ui_color":"text-slate-400","ui_bg":"bg-slate-400/20","prefix":"Gram"},{"id":87,"asset_code":"VAKIFBANK_GG","buy_price":138,"sell_price":183,"updated_at":"2026-01-28T20:30:34.234+00:00","name":"VakıfBank Gram Gümüş","category":"BANKAGUMUS","category_display_name":"Banka Gümüş","live_data":true,"icon_path":"icons/silver.png","ui_color":"text-slate-400","ui_bg":"bg-slate-400/20","prefix":"Gram"},{"id":88,"asset_code":"VAKIFKATILIM_GG","buy_price":157.47,"sell_price":162.28,"updated_at":"2026-01-28T20:30:34.234+00:00","name":"Vakıf Katılım Gram Gümüş","category":"BANKAGUMUS","category_display_name":"Banka Gümüş","live_data":true,"icon_path":"icons/silver.png","ui_color":"text-slate-400","ui_bg":"bg-slate-400/20","prefix":"Gram"},{"id":89,"asset_code":"YAPIKREDI_GG","buy_price":156.01,"sell_price":165.09,"updated_at":"2026-01-28T20:30:34.234+00:00","name":"Yapı Kredi Gram Gümüş","category":"BANKAGUMUS","category_display_name":"Banka Gümüş","live_data":true,"icon_path":"icons/silver.png","ui_color":"text-slate-400","ui_bg":"bg-slate-400/20","prefix":"Gram"},{"id":90,"asset_code":"ZIRAATKATILIM_GG","buy_price":143.67,"sell_price":181.57,"updated_at":"2026-01-28T20:30:34.234+00:00","name":"Ziraat Katılım Gram Gümüş","category":"BANKAGUMUS","category_display_name":"Banka Gümüş","live_data":true,"icon_path":"icons/silver.png","ui_color":"text-slate-400","ui_bg":"bg-slate-400/20","prefix":"Gram"},{"id":92,"asset_code":"DOVIZ_DOLAR","buy_price":43.3939,"sell_price":43.4154,"updated_at":"2026-01-28T20:30:42.558+00:00","name":"Dolar","category":"DOVIZ","category_display_name":"Doviz","live_data":true,"icon_path":"icons/dollar-symbol.png","ui_color":"bg-green-400","ui_bg":"bg-green-400/20","prefix":""},{"id":93,"asset_code":"DOVIZ_EURO","buy_price":51.8669,"sell_price":51.8944,"updated_at":"2026-01-28T20:30:42.559+00:00","name":"Euro","category":"DOVIZ","category_display_name":"Doviz","live_data":true,"icon_path":"icons/euro.png","ui_color":"bg-yellow-400","ui_bg":"bg-yellow-400/20","prefix":""},{"id":76,"asset_code":"DOVIZ_STERLIN","buy_price":59.9097,"sell_price":59.9628,"updated_at":"2026-01-28T20:30:42.559+00:00","name":"Sterlin","category":"DOVIZ","category_display_name":"Doviz","live_data":true,"icon_path":"icons/pound-sign.png","ui_color":"text-blue-400","ui_bg":"bg-blue-400/20","prefix":""}]