[{"id":1,"asset_code":"5GR22AYARBILEZIK","buy_price":33309.6,"sell_price":35293.65,"updated_at":"2026-02-03T21:00:18.262+00:00","name":"5 Gr 22 Ayar Bilezik","category":"22AYAR","category_display_name":"22 Ayar","live_data":false,"icon_path":"icons/ring.png","ui_color":"text-amber-500","ui_bg":"bg-amber-500/20","prefix":"Adet","order":0},{"id":2,"asset_code":"7GR22AYARBILEZIK","buy_price":46633.44,"sell_price":49411.11,"updated_at":"2026-02-03T21:00:18.262+00:00","name":"7 Gr 22 Ayar Bilezik","category":"22AYAR","category_display_name":"22 Ayar","live_data":false,"icon_path":"icons/ring.png","ui_color":"text-amber-500","ui_bg":"bg-amber-500/20","prefix":"Adet","order":0},{"id":3,"asset_code":"10GR22AYARBILEZIK","buy_price":66619.2,"sell_price":70587.3,"updated_at":"2026-02-03T21:00:18.262+00:00","name":"10 Gr 22 Ayar Bilezik","category":"22AYAR","category_display_name":"22 Ayar","live_data":false,"icon_path":"icons/ring.png","ui_color":"text-amber-500","ui_bg":"bg-amber-500/20","prefix":"Adet","order":0},{"id":4,"asset_code":"15GR22AYARBILEZIK","buy_price":99928.8,"sell_price":105880.95,"updated_at":"2026-02-03T21:00:18.262+00:00","name":"15 Gr 22 Ayar Bilezik","category":"22AYAR","category_display_name":"22 Ayar","live_data":false,"icon_path":"icons/ring.png","ui_color":"text-amber-500","ui_bg":"bg-amber-500/20","prefix":"Adet","order":0},{"id":5,"asset_code":"20GR22AYARBILEZIK","buy_price":133238.4,"sell_price":141174.6,"updated_at":"2026-02-03T21:00:18.262+00:00","name":"20 Gr 22 Ayar Bilezik","category":"22AYAR","category_display_name":"22 Ayar","live_data":false,"icon_path":"icons/ring.png","ui_color":"text-amber-500","ui_bg":"bg-amber-500/20","prefix":"Adet","order":0},{"id":6,"asset_code":"25GR22AYARBILEZIK","buy_price":166548,"sell_price":176468.25,"updated_at":"2026-02-03T21:00:18.262+00:00","name":"25 Gr 22 Ayar Bilezik","category":"22AYAR","category_display_name":"22 Ayar","live_data":false,"icon_path":"icons/ring.png","ui_color":"text-amber-500","ui_bg":"bg-amber-500/20","prefix":"Adet","order":0},{"id":7,"asset_code":"30GR22AYARBILEZIK","buy_price":199857.6,"sell_price":211761.9,"updated_at":"2026-02-03T21:00:18.262+00:00","name":"30 Gr 22 Ayar Bilezik","category":"22AYAR","category_display_name":"22 Ayar","live_data":false,"icon_path":"icons/ring.png","ui_color":"text-amber-500","ui_bg":"bg-amber-500/20","prefix":"Adet","order":0},{"id":8,"asset_code":"5GR14AYARBILEZIK","buy_price":20204.35,"sell_price":26716.7,"updated_at":"2026-02-03T21:00:18.262+00:00","name":"5 Gr 14 Ayar Bilezik","category":"14AYAR","category_display_name":"14 Ayar","live_data":false,"icon_path":"icons/ring.png","ui_color":"text-amber-500","ui_bg":"bg-amber-500/20","prefix":"Adet","order":0},{"id":9,"asset_code":"7GR14AYARBILEZIK","buy_price":28286.09,"sell_price":37403.38,"updated_at":"2026-02-03T21:00:18.262+00:00","name":"7 Gr 14 Ayar Bilezik","category":"14AYAR","category_display_name":"14 Ayar","live_data":false,"icon_path":"icons/ring.png","ui_color":"text-amber-500","ui_bg":"bg-amber-500/20","prefix":"Adet","order":0},{"id":10,"asset_code":"10GR14AYARBILEZIK","buy_price":40408.7,"sell_price":53433.4,"updated_at":"2026-02-03T21:00:18.262+00:00","name":"10 Gr 14 Ayar Bilezik","category":"14AYAR","category_display_name":"14 Ayar","live_data":false,"icon_path":"icons/ring.png","ui_color":"text-amber-500","ui_bg":"bg-amber-500/20","prefix":"Adet","order":0},{"id":14,"asset_code":"15GR14AYARBILEZIK","buy_price":60613.05,"sell_price":80150.1,"updated_at":"2026-02-03T21:00:18.262+00:00","name":"15 Gr 14 Ayar Bilezik","category":"14AYAR","category_display_name":"14 Ayar","live_data":false,"icon_path":"icons/ring.png","ui_color":"text-amber-500","ui_bg":"bg-amber-500/20","prefix":"Adet","order":0},{"id":15,"asset_code":"20GR14AYARBILEZIK","buy_price":80817.4,"sell_price":106866.8,"updated_at":"2026-02-03T21:00:18.262+00:00","name":"20 Gr 14 Ayar Bilezik","category":"14AYAR","category_display_name":"14 Ayar","live_data":false,"icon_path":"icons/ring.png","ui_color":"text-amber-500","ui_bg":"bg-amber-500/20","prefix":"Adet","order":0},{"id":16,"asset_code":"25GR14AYARBILEZIK","buy_price":101021.75,"sell_price":133583.5,"updated_at":"2026-02-03T21:00:18.262+00:00","name":"25 Gr 14 Ayar Bilezik","category":"14AYAR","category_display_name":"14 Ayar","live_data":false,"icon_path":"icons/ring.png","ui_color":"text-amber-500","ui_bg":"bg-amber-500/20","prefix":"Adet","order":0},{"id":17,"asset_code":"30GR14AYARBILEZIK","buy_price":121226.1,"sell_price":160300.2,"updated_at":"2026-02-03T21:00:18.262+00:00","name":"30 Gr 14 Ayar Bilezik","category":"14AYAR","category_display_name":"14 Ayar","live_data":false,"icon_path":"icons/ring.png","ui_color":"text-amber-500","ui_bg":"bg-amber-500/20","prefix":"Adet","order":0},{"id":18,"asset_code":"2.5GRKULCEALTIN","buy_price":18270.6,"sell_price":18740.15,"updated_at":"2026-02-03T21:00:18.262+00:00","name":"2.5 Gram Külçe Altın","category":"KULCEALTIN","category_display_name":"Külçe Altın","live_data":false,"icon_path":"icons/gold.png","ui_color":"text-amber-500","ui_bg":"bg-amber-500/20","prefix":"Adet","order":0},{"id":19,"asset_code":"5GRKULCEALTIN","buy_price":36541.2,"sell_price":37480.3,"updated_at":"2026-02-03T21:00:18.262+00:00","name":"5 Gram Külçe Altın","category":"KULCEALTIN","category_display_name":"Külçe Altın","live_data":false,"icon_path":"icons/gold.png","ui_color":"text-amber-500","ui_bg":"bg-amber-500/20","prefix":"Adet","order":0},{"id":20,"asset_code":"10GRKULCEALTIN","buy_price":73082.4,"sell_price":74960.6,"updated_at":"2026-02-03T21:00:18.262+00:00","name":"10 Gram Külçe Altın","category":"KULCEALTIN","category_display_name":"Külçe Altın","live_data":false,"icon_path":"icons/gold.png","ui_color":"text-amber-500","ui_bg":"bg-amber-500/20","prefix":"Adet","order":0},{"id":21,"asset_code":"15GRKULCEALTIN","buy_price":109623.6,"sell_price":112440.9,"updated_at":"2026-02-03T21:00:18.262+00:00","name":"15 Gram Külçe Altın","category":"KULCEALTIN","category_display_name":"Külçe Altın","live_data":false,"icon_path":"icons/gold.png","ui_color":"text-amber-500","ui_bg":"bg-amber-500/20","prefix":"Adet","order":0},{"id":22,"asset_code":"20GRKULCEALTIN","buy_price":146164.8,"sell_price":149921.2,"updated_at":"2026-02-03T21:00:18.262+00:00","name":"20 Gram Külçe Altın","category":"KULCEALTIN","category_display_name":"Külçe Altın","live_data":false,"icon_path":"icons/gold.png","ui_color":"text-amber-500","ui_bg":"bg-amber-500/20","prefix":"Adet","order":0},{"id":23,"asset_code":"25GRKULCEALTIN","buy_price":182706,"sell_price":187401.5,"updated_at":"2026-02-03T21:00:18.262+00:00","name":"25 Gram Külçe Altın","category":"KULCEALTIN","category_display_name":"Külçe Altın","live_data":false,"icon_path":"icons/gold.png","ui_color":"text-amber-500","ui_bg":"bg-amber-500/20","prefix":"Adet","order":0},{"id":24,"asset_code":"50GRKULCEALTIN","buy_price":365412,"sell_price":374803,"updated_at":"2026-02-03T21:00:18.262+00:00","name":"50 Gram Külçe Altın","category":"KULCEALTIN","category_display_name":"Külçe Altın","live_data":false,"icon_path":"icons/gold.png","ui_color":"text-amber-500","ui_bg":"bg-amber-500/20","prefix":"Adet","order":0},{"id":25,"asset_code":"100GRKULCEALTIN","buy_price":730824,"sell_price":749606,"updated_at":"2026-02-03T21:00:18.262+00:00","name":"100 Gram Külçe Altın","category":"KULCEALTIN","category_display_name":"Külçe Altın","live_data":false,"icon_path":"icons/gold.png","ui_color":"text-amber-500","ui_bg":"bg-amber-500/20","prefix":"Adet","order":0},{"id":26,"asset_code":"200GRKULCEALTIN","buy_price":1461648,"sell_price":1499212,"updated_at":"2026-02-03T21:00:18.262+00:00","name":"200 Gram Külçe Altın","category":"KULCEALTIN","category_display_name":"Külçe Altın","live_data":false,"icon_path":"icons/gold.png","ui_color":"text-amber-500","ui_bg":"bg-amber-500/20","prefix":"Adet","order":0},{"id":27,"asset_code":"250GRKULCEALTIN","buy_price":1827060,"sell_price":1874015,"updated_at":"2026-02-03T21:00:18.262+00:00","name":"250 Gram Külçe Altın","category":"KULCEALTIN","category_display_name":"Külçe Altın","live_data":false,"icon_path":"icons/gold.png","ui_color":"text-amber-500","ui_bg":"bg-amber-500/20","prefix":"Adet","order":0},{"id":28,"asset_code":"500GRKULCEALTIN","buy_price":3654120,"sell_price":3748030,"updated_at":"2026-02-03T21:00:18.262+00:00","name":"500 Gram Külçe Altın","category":"KULCEALTIN","category_display_name":"Külçe Altın","live_data":false,"icon_path":"icons/gold.png","ui_color":"text-amber-500","ui_bg":"bg-amber-500/20","prefix":"Adet","order":0},{"id":29,"asset_code":"1000GRKULCEALTIN","buy_price":7308240,"sell_price":7496060,"updated_at":"2026-02-03T21:00:18.262+00:00","name":"1000 Gram Külçe Altın","category":"KULCEALTIN","category_display_name":"Külçe Altın","live_data":false,"icon_path":"icons/gold.png","ui_color":"text-amber-500","ui_bg":"bg-amber-500/20","prefix":"Adet","order":0},{"id":30,"asset_code":"2.5GRKULCEGUMUS","buy_price":311.45,"sell_price":375.85,"updated_at":"2026-02-03T21:00:18.262+00:00","name":"2.5 Gram Külçe Gümüş","category":"KULCEGUMUS","category_display_name":"Külçe Gümüş","live_data":false,"icon_path":"icons/silver.png","ui_color":"text-slate-400","ui_bg":"bg-slate-400/20","prefix":"Adet","order":0},{"id":31,"asset_code":"5GRKULCEGUMUS","buy_price":622.9,"sell_price":751.7,"updated_at":"2026-02-03T21:00:18.262+00:00","name":"5 Gram Külçe Gümüş","category":"KULCEGUMUS","category_display_name":"Külçe Gümüş","live_data":false,"icon_path":"icons/silver.png","ui_color":"text-slate-400","ui_bg":"bg-slate-400/20","prefix":"Adet","order":0},{"id":32,"asset_code":"10GRKULCEGUMUS","buy_price":1245.8,"sell_price":1503.4,"updated_at":"2026-02-03T21:00:18.262+00:00","name":"10 Gram Külçe Gümüş","category":"KULCEGUMUS","category_display_name":"Külçe Gümüş","live_data":false,"icon_path":"icons/silver.png","ui_color":"text-slate-400","ui_bg":"bg-slate-400/20","prefix":"Adet","order":0},{"id":33,"asset_code":"15GRKULCEGUMUS","buy_price":1868.7,"sell_price":2255.1,"updated_at":"2026-02-03T21:00:18.262+00:00","name":"15 Gram Külçe Gümüş","category":"KULCEGUMUS","category_display_name":"Külçe Gümüş","live_data":false,"icon_path":"icons/silver.png","ui_color":"text-slate-400","ui_bg":"bg-slate-400/20","prefix":"Adet","order":0},{"id":34,"asset_code":"20GRKULCEGUMUS","buy_price":2491.6,"sell_price":3006.8,"updated_at":"2026-02-03T21:00:18.262+00:00","name":"20 Gram Külçe Gümüş","category":"KULCEGUMUS","category_display_name":"Külçe Gümüş","live_data":false,"icon_path":"icons/silver.png","ui_color":"text-slate-400","ui_bg":"bg-slate-400/20","prefix":"Adet","order":0},{"id":35,"asset_code":"25GRKULCEGUMUS","buy_price":3114.5,"sell_price":3758.5,"updated_at":"2026-02-03T21:00:18.262+00:00","name":"25 Gram Külçe Gümüş","category":"KULCEGUMUS","category_display_name":"Külçe Gümüş","live_data":false,"icon_path":"icons/silver.png","ui_color":"text-slate-400","ui_bg":"bg-slate-400/20","prefix":"Adet","order":0},{"id":36,"asset_code":"50GRKULCEGUMUS","buy_price":6229,"sell_price":7517,"updated_at":"2026-02-03T21:00:18.262+00:00","name":"50 Gram Külçe Gümüş","category":"KULCEGUMUS","category_display_name":"Külçe Gümüş","live_data":false,"icon_path":"icons/silver.png","ui_color":"text-slate-400","ui_bg":"bg-slate-400/20","prefix":"Adet","order":0},{"id":37,"asset_code":"100GRKULCEGUMUS","buy_price":12458,"sell_price":15034,"updated_at":"2026-02-03T21:00:18.262+00:00","name":"100 Gram Külçe Gümüş","category":"KULCEGUMUS","category_display_name":"Külçe Gümüş","live_data":false,"icon_path":"icons/silver.png","ui_color":"text-slate-400","ui_bg":"bg-slate-400/20","prefix":"Adet","order":0},{"id":38,"asset_code":"200GRKULCEGUMUS","buy_price":24916,"sell_price":30068,"updated_at":"2026-02-03T21:00:18.262+00:00","name":"200 Gram Külçe Gümüş","category":"KULCEGUMUS","category_display_name":"Külçe Gümüş","live_data":false,"icon_path":"icons/silver.png","ui_color":"text-slate-400","ui_bg":"bg-slate-400/20","prefix":"Adet","order":0},{"id":39,"asset_code":"250GRKULCEGUMUS","buy_price":31145,"sell_price":37585,"updated_at":"2026-02-03T21:00:18.262+00:00","name":"250 Gram Külçe Gümüş","category":"KULCEGUMUS","category_display_name":"Külçe Gümüş","live_data":false,"icon_path":"icons/silver.png","ui_color":"text-slate-400","ui_bg":"bg-slate-400/20","prefix":"Adet","order":0},{"id":40,"asset_code":"500GRKULCEGUMUS","buy_price":62290,"sell_price":75170,"updated_at":"2026-02-03T21:00:18.262+00:00","name":"500 Gram Külçe Gümüş","category":"KULCEGUMUS","category_display_name":"Külçe Gümüş","live_data":false,"icon_path":"icons/silver.png","ui_color":"text-slate-400","ui_bg":"bg-slate-400/20","prefix":"Adet","order":0},{"id":41,"asset_code":"1000GRKULCEGUMUS","buy_price":124580,"sell_price":150340,"updated_at":"2026-02-03T21:00:18.262+00:00","name":"1000 Gram Külçe Gümüş","category":"KULCEGUMUS","category_display_name":"Külçe Gümüş","live_data":false,"icon_path":"icons/silver.png","ui_color":"text-slate-400","ui_bg":"bg-slate-400/20","prefix":"Adet","order":0},{"id":95,"asset_code":"KRIPTO_BTC","buy_price":3324999,"sell_price":3325000,"updated_at":"2026-02-03T21:00:14.423+00:00","name":"Bitcoin","category":"KRIPTO","category_display_name":"Kripto","live_data":true,"icon_path":"icons/bitcoin.png","ui_color":"text-amber-500","ui_bg":"bg-amber-500/20","prefix":"Adet","order":180},{"id":96,"asset_code":"KRIPTO_ETH","buy_price":99977,"sell_price":99978,"updated_at":"2026-02-03T21:00:14.424+00:00","name":"Ethereum","category":"KRIPTO","category_display_name":"Kripto","live_data":true,"icon_path":"icons/ethereum.png","ui_color":"bg-blue-500","ui_bg":"bg-blue-500/20","prefix":"Adet","order":170},{"id":55,"asset_code":"AKBANK_GA","buy_price":6604.27,"sell_price":7238.19,"updated_at":"2026-02-03T21:00:14.425+00:00","name":"Akbank Gram Altın","category":"BANKAALTIN","category_display_name":"Banka Altın","live_data":true,"icon_path":"icons/gold.png","ui_color":"text-amber-500","ui_bg":"bg-amber-500/20","prefix":"Gram","order":0},{"id":56,"asset_code":"ALBARAKA_GA","buy_price":6676.23,"sell_price":7097.23,"updated_at":"2026-02-03T21:00:14.425+00:00","name":"Albaraka Türk Gram Altın","category":"BANKAALTIN","category_display_name":"Banka Altın","live_data":true,"icon_path":"icons/gold.png","ui_color":"text-amber-500","ui_bg":"bg-amber-500/20","prefix":"Gram","order":0},{"id":57,"asset_code":"ALTERNATIF_GA","buy_price":6310.51,"sell_price":7272.99,"updated_at":"2026-02-03T21:00:14.425+00:00","name":"Alternatif Bank Gram Altın","category":"BANKAALTIN","category_display_name":"Banka Altın","live_data":true,"icon_path":"icons/gold.png","ui_color":"text-amber-500","ui_bg":"bg-amber-500/20","prefix":"Gram","order":0},{"id":58,"asset_code":"ANADOLUBANK_GA","buy_price":6413.36,"sell_price":7325.93,"updated_at":"2026-02-03T21:00:14.425+00:00","name":"Anadolubank Gram Altın","category":"BANKAALTIN","category_display_name":"Banka Altın","live_data":true,"icon_path":"icons/gold.png","ui_color":"text-amber-500","ui_bg":"bg-amber-500/20","prefix":"Gram","order":0},{"id":59,"asset_code":"CEBTETEB_GA","buy_price":6112.18,"sell_price":7673.98,"updated_at":"2026-02-03T21:00:14.425+00:00","name":"CEPTETEB Gram Altın","category":"BANKAALTIN","category_display_name":"Banka Altın","live_data":true,"icon_path":"icons/gold.png","ui_color":"text-amber-500","ui_bg":"bg-amber-500/20","prefix":"Gram","order":0},{"id":60,"asset_code":"DENIZBANK_GA","buy_price":6636.3,"sell_price":7261.1,"updated_at":"2026-02-03T21:00:14.425+00:00","name":"DenizBank Gram Altın","category":"BANKAALTIN","category_display_name":"Banka Altın","live_data":true,"icon_path":"icons/gold.png","ui_color":"text-amber-500","ui_bg":"bg-amber-500/20","prefix":"Gram","order":0},{"id":61,"asset_code":"ENPARA_GA","buy_price":6719.7,"sell_price":7109.85,"updated_at":"2026-02-03T21:00:14.425+00:00","name":"Enpara Gram Altın","category":"BANKAALTIN","category_display_name":"Banka Altın","live_data":true,"icon_path":"icons/gold.png","ui_color":"text-amber-500","ui_bg":"bg-amber-500/20","prefix":"Gram","order":0},{"id":62,"asset_code":"FIBABANKA_GA","buy_price":6878.54,"sell_price":6934.59,"updated_at":"2026-02-03T21:00:14.425+00:00","name":"Fibabanka Gram Altın","category":"BANKAALTIN","category_display_name":"Banka Altın","live_data":true,"icon_path":"icons/gold.png","ui_color":"text-amber-500","ui_bg":"bg-amber-500/20","prefix":"Gram","order":0},{"id":63,"asset_code":"GARANTI_GA","buy_price":6673.81,"sell_price":7252.67,"updated_at":"2026-02-03T21:00:14.425+00:00","name":"Garanti BBVA Gram Altın","category":"BANKAALTIN","category_display_name":"Banka Altın","live_data":true,"icon_path":"icons/gold.png","ui_color":"text-amber-500","ui_bg":"bg-amber-500/20","prefix":"Gram","order":0},{"id":64,"asset_code":"HALKBANK_GA","buy_price":6495.17,"sell_price":7241.42,"updated_at":"2026-02-03T21:00:14.425+00:00","name":"Halkbank Gram Altın","category":"BANKAALTIN","category_display_name":"Banka Altın","live_data":true,"icon_path":"icons/gold.png","ui_color":"text-amber-500","ui_bg":"bg-amber-500/20","prefix":"Gram","order":0},{"id":65,"asset_code":"HSBC_GA","buy_price":6772.97,"sell_price":7157.84,"updated_at":"2026-02-03T21:00:14.425+00:00","name":"HSBC Gram Altın","category":"BANKAALTIN","category_display_name":"Banka Altın","live_data":true,"icon_path":"icons/gold.png","ui_color":"text-amber-500","ui_bg":"bg-amber-500/20","prefix":"Gram","order":0},{"id":66,"asset_code":"ING_GA","buy_price":6766.8,"sell_price":7060.14,"updated_at":"2026-02-03T21:00:14.425+00:00","name":"ING Bank Gram Altın","category":"BANKAALTIN","category_display_name":"Banka Altın","live_data":true,"icon_path":"icons/gold.png","ui_color":"text-amber-500","ui_bg":"bg-amber-500/20","prefix":"Gram","order":0},{"id":67,"asset_code":"KUVEYTTURK_GA","buy_price":6786.13,"sell_price":6987.3,"updated_at":"2026-02-03T21:00:14.425+00:00","name":"Kuveyt Türk Gram Altın","category":"BANKAALTIN","category_display_name":"Banka Altın","live_data":true,"icon_path":"icons/gold.png","ui_color":"text-amber-500","ui_bg":"bg-amber-500/20","prefix":"Gram","order":0},{"id":68,"asset_code":"QNBFB_GA","buy_price":6505.9,"sell_price":7265.32,"updated_at":"2026-02-03T21:00:14.425+00:00","name":"QNB Finansbank Gram Altın","category":"BANKAALTIN","category_display_name":"Banka Altın","live_data":true,"icon_path":"icons/gold.png","ui_color":"text-amber-500","ui_bg":"bg-amber-500/20","prefix":"Gram","order":0},{"id":69,"asset_code":"SEKERBANK_GA","buy_price":6659.59,"sell_price":7093.35,"updated_at":"2026-02-03T21:00:14.425+00:00","name":"Şekerbank Gram Altın","category":"BANKAALTIN","category_display_name":"Banka Altın","live_data":true,"icon_path":"icons/gold.png","ui_color":"text-amber-500","ui_bg":"bg-amber-500/20","prefix":"Gram","order":0},{"id":70,"asset_code":"TURKIYEFINANS_GA","buy_price":6830.67,"sell_price":7034.15,"updated_at":"2026-02-03T21:00:14.425+00:00","name":"Türkiye Finans Gram Altın","category":"BANKAALTIN","category_display_name":"Banka Altın","live_data":true,"icon_path":"icons/gold.png","ui_color":"text-amber-500","ui_bg":"bg-amber-500/20","prefix":"Gram","order":0},{"id":71,"asset_code":"VAKIFBANK_GA","buy_price":6381.63,"sell_price":7301.63,"updated_at":"2026-02-03T21:00:14.425+00:00","name":"VakıfBank Gram Altın","category":"BANKAALTIN","category_display_name":"Banka Altın","live_data":true,"icon_path":"icons/gold.png","ui_color":"text-amber-500","ui_bg":"bg-amber-500/20","prefix":"Gram","order":0},{"id":72,"asset_code":"VAKIFKATILIM_GA","buy_price":6710.6,"sell_price":7006.29,"updated_at":"2026-02-03T21:00:14.425+00:00","name":"Vakıf Katılım Gram Altın","category":"BANKAALTIN","category_display_name":"Banka Altın","live_data":true,"icon_path":"icons/gold.png","ui_color":"text-amber-500","ui_bg":"bg-amber-500/20","prefix":"Gram","order":0},{"id":73,"asset_code":"YAPIKREDI_GA","buy_price":6747.47,"sell_price":7069.91,"updated_at":"2026-02-03T21:00:14.425+00:00","name":"Yapı Kredi Gram Altın","category":"BANKAALTIN","category_display_name":"Banka Altın","live_data":true,"icon_path":"icons/gold.png","ui_color":"text-amber-500","ui_bg":"bg-amber-500/20","prefix":"Gram","order":0},{"id":74,"asset_code":"ZIRAAT_GA","buy_price":6613.57,"sell_price":7570.47,"updated_at":"2026-02-03T21:00:14.425+00:00","name":"Ziraat Bankası Gram Altın","category":"BANKAALTIN","category_display_name":"Banka Altın","live_data":true,"icon_path":"icons/gold.png","ui_color":"text-amber-500","ui_bg":"bg-amber-500/20","prefix":"Gram","order":0},{"id":75,"asset_code":"ZIRAATKATILIM_GA","buy_price":6138.15,"sell_price":7740.95,"updated_at":"2026-02-03T21:00:14.426+00:00","name":"Ziraat Katılım Gram Altın","category":"BANKAALTIN","category_display_name":"Banka Altın","live_data":true,"icon_path":"icons/gold.png","ui_color":"text-amber-500","ui_bg":"bg-amber-500/20","prefix":"Gram","order":0},{"id":42,"asset_code":"HAS_GA","buy_price":7308.24,"sell_price":7496.06,"updated_at":"2026-02-03T21:00:14.426+00:00","name":"Gram Külçe Altın","category":"KULCEALTIN","category_display_name":"Külçe Altın","live_data":true,"icon_path":"icons/gold.png","ui_color":"text-amber-500","ui_bg":"bg-amber-500/20","prefix":"Adet","order":200},{"id":43,"asset_code":"CEYREK_YENI","buy_price":11936,"sell_price":12262,"updated_at":"2026-02-03T21:00:14.426+00:00","name":"Çeyrek Altın","category":"ZIYNET","category_display_name":"Ziynet","live_data":true,"icon_path":"icons/ceyrek_yarim_tam_ata.png","ui_color":"text-amber-500","ui_bg":"bg-amber-500/20","prefix":"Adet","order":165},{"id":44,"asset_code":"CEYREK_ESKI","buy_price":11827,"sell_price":12225,"updated_at":"2026-02-03T21:00:14.426+00:00","name":"Çeyrek Altın Eski","category":"ZIYNET","category_display_name":"Ziynet","live_data":true,"icon_path":"icons/ceyrek_yarim_tam_ata.png","ui_color":"text-amber-500","ui_bg":"bg-amber-500/20","prefix":"Adet","order":160},{"id":45,"asset_code":"YARIM_YENI","buy_price":23873,"sell_price":24525,"updated_at":"2026-02-03T21:00:14.426+00:00","name":"Yarım Altın","category":"ZIYNET","category_display_name":"Ziynet","live_data":true,"icon_path":"icons/ceyrek_yarim_tam_ata.png","ui_color":"text-amber-500","ui_bg":"bg-amber-500/20","prefix":"Adet","order":155},{"id":46,"asset_code":"YARIM_ESKI","buy_price":23580,"sell_price":24450,"updated_at":"2026-02-03T21:00:14.426+00:00","name":"Yarım Altın Eski","category":"ZIYNET","category_display_name":"Ziynet","live_data":true,"icon_path":"icons/ceyrek_yarim_tam_ata.png","ui_color":"text-amber-500","ui_bg":"bg-amber-500/20","prefix":"Adet","order":150},{"id":47,"asset_code":"TAM_YENI","buy_price":47599,"sell_price":48901,"updated_at":"2026-02-03T21:00:14.426+00:00","name":"Tam Altın","category":"ZIYNET","category_display_name":"Ziynet","live_data":true,"icon_path":"icons/ceyrek_yarim_tam_ata.png","ui_color":"text-amber-500","ui_bg":"bg-amber-500/20","prefix":"Adet","order":145},{"id":48,"asset_code":"TAM_ESKI","buy_price":47160,"sell_price":48379,"updated_at":"2026-02-03T21:00:14.426+00:00","name":"Tam Altın Eski","category":"ZIYNET","category_display_name":"Ziynet","live_data":true,"icon_path":"icons/ceyrek_yarim_tam_ata.png","ui_color":"text-amber-500","ui_bg":"bg-amber-500/20","prefix":"Adet","order":140},{"id":49,"asset_code":"ATA_YENI","buy_price":48881,"sell_price":50167,"updated_at":"2026-02-03T21:00:14.426+00:00","name":"Ata Altın","category":"ZIYNET","category_display_name":"Ziynet","live_data":true,"icon_path":"icons/ceyrek_yarim_tam_ata.png","ui_color":"text-amber-500","ui_bg":"bg-amber-500/20","prefix":"Adet","order":135},{"id":50,"asset_code":"ATA_ESKI","buy_price":48881,"sell_price":50093,"updated_at":"2026-02-03T21:00:14.426+00:00","name":"Ata Altın Eski","category":"ZIYNET","category_display_name":"Ziynet","live_data":true,"icon_path":"icons/ceyrek_yarim_tam_ata.png","ui_color":"text-amber-500","ui_bg":"bg-amber-500/20","prefix":"Adet","order":130},{"id":51,"asset_code":"AYAR14","buy_price":4040.87,"sell_price":5343.34,"updated_at":"2026-02-03T21:00:14.426+00:00","name":"14 Ayar","category":"14AYAR","category_display_name":"14 Ayar","live_data":true,"icon_path":"icons/ring.png","ui_color":"text-amber-500","ui_bg":"bg-amber-500/20","prefix":"Adet","order":125},{"id":52,"asset_code":"AYAR22","buy_price":6661.92,"sell_price":7058.73,"updated_at":"2026-02-03T21:00:14.426+00:00","name":"22 Ayar","category":"22AYAR","category_display_name":"22 Ayar","live_data":true,"icon_path":"icons/ring.png","ui_color":"text-amber-500","ui_bg":"bg-amber-500/20","prefix":"Adet","order":120},{"id":53,"asset_code":"HAS_GG","buy_price":124.58,"sell_price":150.34,"updated_at":"2026-02-03T21:00:14.426+00:00","name":"Gram Külçe Gümüş","category":"KULCEGUMUS","category_display_name":"Külçe Gümüş","live_data":true,"icon_path":"icons/silver.png","ui_color":"text-slate-400","ui_bg":"bg-slate-400/20","prefix":"Adet","order":190},{"id":77,"asset_code":"ISBANK_GA","buy_price":6491.44,"sell_price":7268.63,"updated_at":"2026-02-03T21:00:18.287+00:00","name":"İş Bankası Gram Altın","category":"BANKAALTIN","category_display_name":"Banka Altın","live_data":true,"icon_path":"icons/gold.png","ui_color":"text-amber-500","ui_bg":"bg-amber-500/20","prefix":"Gram","order":0},{"id":78,"asset_code":"AKBANK_GG","buy_price":114.16,"sell_price":125.25,"updated_at":"2026-02-03T21:00:27.605+00:00","name":"Akbank Gram Gümüş","category":"BANKAGUMUS","category_display_name":"Banka Gümüş","live_data":true,"icon_path":"icons/silver.png","ui_color":"text-slate-400","ui_bg":"bg-slate-400/20","prefix":"Gram","order":0},{"id":79,"asset_code":"ALBARAKA_GG","buy_price":114.26,"sell_price":122.98,"updated_at":"2026-02-03T21:00:27.605+00:00","name":"Albaraka Türk Gram Gümüş","category":"BANKAGUMUS","category_display_name":"Banka Gümüş","live_data":true,"icon_path":"icons/silver.png","ui_color":"text-slate-400","ui_bg":"bg-slate-400/20","prefix":"Gram","order":0},{"id":80,"asset_code":"ANADOLUBANK_GG","buy_price":96.33,"sell_price":140.85,"updated_at":"2026-02-03T21:00:27.605+00:00","name":"Anadolubank Gram Gümüş","category":"BANKAGUMUS","category_display_name":"Banka Gümüş","live_data":true,"icon_path":"icons/silver.png","ui_color":"text-slate-400","ui_bg":"bg-slate-400/20","prefix":"Gram","order":0},{"id":81,"asset_code":"DENIZBANK_GG","buy_price":113.9,"sell_price":124.76,"updated_at":"2026-02-03T21:00:27.607+00:00","name":"DenizBank Gram Gümüş","category":"BANKAGUMUS","category_display_name":"Banka Gümüş","live_data":true,"icon_path":"icons/silver.png","ui_color":"text-slate-400","ui_bg":"bg-slate-400/20","prefix":"Gram","order":0},{"id":82,"asset_code":"FIBABANKA_GG","buy_price":118.14,"sell_price":119.07,"updated_at":"2026-02-03T21:00:27.607+00:00","name":"Fibabanka Gram Gümüş","category":"BANKAGUMUS","category_display_name":"Banka Gümüş","live_data":true,"icon_path":"icons/silver.png","ui_color":"text-slate-400","ui_bg":"bg-slate-400/20","prefix":"Gram","order":0},{"id":83,"asset_code":"GARANTI_GG","buy_price":112.99,"sell_price":125.92,"updated_at":"2026-02-03T21:00:27.607+00:00","name":"Garanti BBVA Gram Gümüş","category":"BANKAGUMUS","category_display_name":"Banka Gümüş","live_data":true,"icon_path":"icons/silver.png","ui_color":"text-slate-400","ui_bg":"bg-slate-400/20","prefix":"Gram","order":0},{"id":84,"asset_code":"HSBC_GG","buy_price":116.41,"sell_price":123.38,"updated_at":"2026-02-03T21:00:27.607+00:00","name":"HSBC Gram Gümüş","category":"BANKAGUMUS","category_display_name":"Banka Gümüş","live_data":true,"icon_path":"icons/silver.png","ui_color":"text-slate-400","ui_bg":"bg-slate-400/20","prefix":"Gram","order":0},{"id":85,"asset_code":"KUVEYTTURK_GG","buy_price":117.4,"sell_price":120.92,"updated_at":"2026-02-03T21:00:27.607+00:00","name":"Kuveyt Türk Gram Gümüş","category":"BANKAGUMUS","category_display_name":"Banka Gümüş","live_data":true,"icon_path":"icons/silver.png","ui_color":"text-slate-400","ui_bg":"bg-slate-400/20","prefix":"Gram","order":0},{"id":86,"asset_code":"TURKIYEFINANS_GG","buy_price":118.25,"sell_price":126.27,"updated_at":"2026-02-03T21:00:27.607+00:00","name":"Türkiye Finans Gram Gümüş","category":"BANKAGUMUS","category_display_name":"Banka Gümüş","live_data":true,"icon_path":"icons/silver.png","ui_color":"text-slate-400","ui_bg":"bg-slate-400/20","prefix":"Gram","order":0},{"id":87,"asset_code":"VAKIFBANK_GG","buy_price":100.58,"sell_price":145.58,"updated_at":"2026-02-03T21:00:27.607+00:00","name":"VakıfBank Gram Gümüş","category":"BANKAGUMUS","category_display_name":"Banka Gümüş","live_data":true,"icon_path":"icons/silver.png","ui_color":"text-slate-400","ui_bg":"bg-slate-400/20","prefix":"Gram","order":0},{"id":88,"asset_code":"VAKIFKATILIM_GG","buy_price":116.96,"sell_price":120.54,"updated_at":"2026-02-03T21:00:27.607+00:00","name":"Vakıf Katılım Gram Gümüş","category":"BANKAGUMUS","category_display_name":"Banka Gümüş","live_data":true,"icon_path":"icons/silver.png","ui_color":"text-slate-400","ui_bg":"bg-slate-400/20","prefix":"Gram","order":0},{"id":89,"asset_code":"YAPIKREDI_GG","buy_price":114.89,"sell_price":123.53,"updated_at":"2026-02-03T21:00:27.607+00:00","name":"Yapı Kredi Gram Gümüş","category":"BANKAGUMUS","category_display_name":"Banka Gümüş","live_data":true,"icon_path":"icons/silver.png","ui_color":"text-slate-400","ui_bg":"bg-slate-400/20","prefix":"Gram","order":0},{"id":90,"asset_code":"ZIRAATKATILIM_GG","buy_price":109.8,"sell_price":138.82,"updated_at":"2026-02-03T21:00:27.607+00:00","name":"Ziraat Katılım Gram Gümüş","category":"BANKAGUMUS","category_display_name":"Banka Gümüş","live_data":true,"icon_path":"icons/silver.png","ui_color":"text-slate-400","ui_bg":"bg-slate-400/20","prefix":"Gram","order":0},{"id":92,"asset_code":"DOVIZ_DOLAR","buy_price":43.4744,"sell_price":43.4885,"updated_at":"2026-02-03T21:00:29.936+00:00","name":"Dolar","category":"DOVIZ","category_display_name":"Doviz","live_data":true,"icon_path":"icons/dollar-symbol.png","ui_color":"bg-green-400","ui_bg":"bg-green-400/20","prefix":"","order":500},{"id":93,"asset_code":"DOVIZ_EURO","buy_price":51.419,"sell_price":51.4514,"updated_at":"2026-02-03T21:00:29.936+00:00","name":"Euro","category":"DOVIZ","category_display_name":"Doviz","live_data":true,"icon_path":"icons/euro.png","ui_color":"bg-yellow-400","ui_bg":"bg-yellow-400/20","prefix":"","order":400},{"id":76,"asset_code":"DOVIZ_STERLIN","buy_price":59.5621,"sell_price":59.634,"updated_at":"2026-02-03T21:00:29.936+00:00","name":"Sterlin","category":"DOVIZ","category_display_name":"Doviz","live_data":true,"icon_path":"icons/pound-sign.png","ui_color":"text-blue-400","ui_bg":"bg-blue-400/20","prefix":"","order":300}]