[{"id":1,"asset_code":"5GR22AYARBILEZIK","buy_price":36267.1,"sell_price":37979.6,"updated_at":"2026-01-29T07:23:06.529+00:00","name":"5 Gr 22 Ayar Bilezik","category":"22AYAR","category_display_name":"22 Ayar","live_data":false,"icon_path":"icons/ring.png","ui_color":"text-amber-500","ui_bg":"bg-amber-500/20","prefix":"Adet"},{"id":2,"asset_code":"7GR22AYARBILEZIK","buy_price":50773.94,"sell_price":53171.44,"updated_at":"2026-01-29T07:23:06.529+00:00","name":"7 Gr 22 Ayar Bilezik","category":"22AYAR","category_display_name":"22 Ayar","live_data":false,"icon_path":"icons/ring.png","ui_color":"text-amber-500","ui_bg":"bg-amber-500/20","prefix":"Adet"},{"id":3,"asset_code":"10GR22AYARBILEZIK","buy_price":72534.2,"sell_price":75959.2,"updated_at":"2026-01-29T07:23:06.529+00:00","name":"10 Gr 22 Ayar Bilezik","category":"22AYAR","category_display_name":"22 Ayar","live_data":false,"icon_path":"icons/ring.png","ui_color":"text-amber-500","ui_bg":"bg-amber-500/20","prefix":"Adet"},{"id":4,"asset_code":"15GR22AYARBILEZIK","buy_price":108801.3,"sell_price":113938.8,"updated_at":"2026-01-29T07:23:06.529+00:00","name":"15 Gr 22 Ayar Bilezik","category":"22AYAR","category_display_name":"22 Ayar","live_data":false,"icon_path":"icons/ring.png","ui_color":"text-amber-500","ui_bg":"bg-amber-500/20","prefix":"Adet"},{"id":5,"asset_code":"20GR22AYARBILEZIK","buy_price":145068.4,"sell_price":151918.4,"updated_at":"2026-01-29T07:23:06.529+00:00","name":"20 Gr 22 Ayar Bilezik","category":"22AYAR","category_display_name":"22 Ayar","live_data":false,"icon_path":"icons/ring.png","ui_color":"text-amber-500","ui_bg":"bg-amber-500/20","prefix":"Adet"},{"id":6,"asset_code":"25GR22AYARBILEZIK","buy_price":181335.5,"sell_price":189898,"updated_at":"2026-01-29T07:23:06.529+00:00","name":"25 Gr 22 Ayar Bilezik","category":"22AYAR","category_display_name":"22 Ayar","live_data":false,"icon_path":"icons/ring.png","ui_color":"text-amber-500","ui_bg":"bg-amber-500/20","prefix":"Adet"},{"id":7,"asset_code":"30GR22AYARBILEZIK","buy_price":217602.6,"sell_price":227877.6,"updated_at":"2026-01-29T07:23:06.529+00:00","name":"30 Gr 22 Ayar Bilezik","category":"22AYAR","category_display_name":"22 Ayar","live_data":false,"icon_path":"icons/ring.png","ui_color":"text-amber-500","ui_bg":"bg-amber-500/20","prefix":"Adet"},{"id":8,"asset_code":"5GR14AYARBILEZIK","buy_price":22024.35,"sell_price":28554.45,"updated_at":"2026-01-29T07:23:06.529+00:00","name":"5 Gr 14 Ayar Bilezik","category":"14AYAR","category_display_name":"14 Ayar","live_data":false,"icon_path":"icons/ring.png","ui_color":"text-amber-500","ui_bg":"bg-amber-500/20","prefix":"Adet"},{"id":9,"asset_code":"7GR14AYARBILEZIK","buy_price":30834.09,"sell_price":39976.23,"updated_at":"2026-01-29T07:23:06.529+00:00","name":"7 Gr 14 Ayar Bilezik","category":"14AYAR","category_display_name":"14 Ayar","live_data":false,"icon_path":"icons/ring.png","ui_color":"text-amber-500","ui_bg":"bg-amber-500/20","prefix":"Adet"},{"id":10,"asset_code":"10GR14AYARBILEZIK","buy_price":44048.7,"sell_price":57108.9,"updated_at":"2026-01-29T07:23:06.529+00:00","name":"10 Gr 14 Ayar Bilezik","category":"14AYAR","category_display_name":"14 Ayar","live_data":false,"icon_path":"icons/ring.png","ui_color":"text-amber-500","ui_bg":"bg-amber-500/20","prefix":"Adet"},{"id":14,"asset_code":"15GR14AYARBILEZIK","buy_price":66073.05,"sell_price":85663.35,"updated_at":"2026-01-29T07:23:06.529+00:00","name":"15 Gr 14 Ayar Bilezik","category":"14AYAR","category_display_name":"14 Ayar","live_data":false,"icon_path":"icons/ring.png","ui_color":"text-amber-500","ui_bg":"bg-amber-500/20","prefix":"Adet"},{"id":15,"asset_code":"20GR14AYARBILEZIK","buy_price":88097.4,"sell_price":114217.8,"updated_at":"2026-01-29T07:23:06.529+00:00","name":"20 Gr 14 Ayar Bilezik","category":"14AYAR","category_display_name":"14 Ayar","live_data":false,"icon_path":"icons/ring.png","ui_color":"text-amber-500","ui_bg":"bg-amber-500/20","prefix":"Adet"},{"id":16,"asset_code":"25GR14AYARBILEZIK","buy_price":110121.75,"sell_price":142772.25,"updated_at":"2026-01-29T07:23:06.529+00:00","name":"25 Gr 14 Ayar Bilezik","category":"14AYAR","category_display_name":"14 Ayar","live_data":false,"icon_path":"icons/ring.png","ui_color":"text-amber-500","ui_bg":"bg-amber-500/20","prefix":"Adet"},{"id":17,"asset_code":"30GR14AYARBILEZIK","buy_price":132146.1,"sell_price":171326.7,"updated_at":"2026-01-29T07:23:06.529+00:00","name":"30 Gr 14 Ayar Bilezik","category":"14AYAR","category_display_name":"14 Ayar","live_data":false,"icon_path":"icons/ring.png","ui_color":"text-amber-500","ui_bg":"bg-amber-500/20","prefix":"Adet"},{"id":18,"asset_code":"2.5GRKULCEALTIN","buy_price":19892.33,"sell_price":20162.33,"updated_at":"2026-01-29T07:23:06.529+00:00","name":"2.5 Gram Külçe Altın","category":"KULCEALTIN","category_display_name":"Külçe Altın","live_data":false,"icon_path":"icons/gold.png","ui_color":"text-amber-500","ui_bg":"bg-amber-500/20","prefix":"Adet"},{"id":19,"asset_code":"5GRKULCEALTIN","buy_price":39784.65,"sell_price":40324.65,"updated_at":"2026-01-29T07:23:06.529+00:00","name":"5 Gram Külçe Altın","category":"KULCEALTIN","category_display_name":"Külçe Altın","live_data":false,"icon_path":"icons/gold.png","ui_color":"text-amber-500","ui_bg":"bg-amber-500/20","prefix":"Adet"},{"id":20,"asset_code":"10GRKULCEALTIN","buy_price":79569.3,"sell_price":80649.3,"updated_at":"2026-01-29T07:23:06.529+00:00","name":"10 Gram Külçe Altın","category":"KULCEALTIN","category_display_name":"Külçe Altın","live_data":false,"icon_path":"icons/gold.png","ui_color":"text-amber-500","ui_bg":"bg-amber-500/20","prefix":"Adet"},{"id":21,"asset_code":"15GRKULCEALTIN","buy_price":119353.95,"sell_price":120973.95,"updated_at":"2026-01-29T07:23:06.529+00:00","name":"15 Gram Külçe Altın","category":"KULCEALTIN","category_display_name":"Külçe Altın","live_data":false,"icon_path":"icons/gold.png","ui_color":"text-amber-500","ui_bg":"bg-amber-500/20","prefix":"Adet"},{"id":22,"asset_code":"20GRKULCEALTIN","buy_price":159138.6,"sell_price":161298.6,"updated_at":"2026-01-29T07:23:06.529+00:00","name":"20 Gram Külçe Altın","category":"KULCEALTIN","category_display_name":"Külçe Altın","live_data":false,"icon_path":"icons/gold.png","ui_color":"text-amber-500","ui_bg":"bg-amber-500/20","prefix":"Adet"},{"id":23,"asset_code":"25GRKULCEALTIN","buy_price":198923.25,"sell_price":201623.25,"updated_at":"2026-01-29T07:23:06.529+00:00","name":"25 Gram Külçe Altın","category":"KULCEALTIN","category_display_name":"Külçe Altın","live_data":false,"icon_path":"icons/gold.png","ui_color":"text-amber-500","ui_bg":"bg-amber-500/20","prefix":"Adet"},{"id":24,"asset_code":"50GRKULCEALTIN","buy_price":397846.5,"sell_price":403246.5,"updated_at":"2026-01-29T07:23:06.529+00:00","name":"50 Gram Külçe Altın","category":"KULCEALTIN","category_display_name":"Külçe Altın","live_data":false,"icon_path":"icons/gold.png","ui_color":"text-amber-500","ui_bg":"bg-amber-500/20","prefix":"Adet"},{"id":25,"asset_code":"100GRKULCEALTIN","buy_price":795693,"sell_price":806493,"updated_at":"2026-01-29T07:23:06.529+00:00","name":"100 Gram Külçe Altın","category":"KULCEALTIN","category_display_name":"Külçe Altın","live_data":false,"icon_path":"icons/gold.png","ui_color":"text-amber-500","ui_bg":"bg-amber-500/20","prefix":"Adet"},{"id":26,"asset_code":"200GRKULCEALTIN","buy_price":1591386,"sell_price":1612986,"updated_at":"2026-01-29T07:23:06.529+00:00","name":"200 Gram Külçe Altın","category":"KULCEALTIN","category_display_name":"Külçe Altın","live_data":false,"icon_path":"icons/gold.png","ui_color":"text-amber-500","ui_bg":"bg-amber-500/20","prefix":"Adet"},{"id":27,"asset_code":"250GRKULCEALTIN","buy_price":1989232.5,"sell_price":2016232.5,"updated_at":"2026-01-29T07:23:06.529+00:00","name":"250 Gram Külçe Altın","category":"KULCEALTIN","category_display_name":"Külçe Altın","live_data":false,"icon_path":"icons/gold.png","ui_color":"text-amber-500","ui_bg":"bg-amber-500/20","prefix":"Adet"},{"id":28,"asset_code":"500GRKULCEALTIN","buy_price":3978465,"sell_price":4032465,"updated_at":"2026-01-29T07:23:06.529+00:00","name":"500 Gram Külçe Altın","category":"KULCEALTIN","category_display_name":"Külçe Altın","live_data":false,"icon_path":"icons/gold.png","ui_color":"text-amber-500","ui_bg":"bg-amber-500/20","prefix":"Adet"},{"id":29,"asset_code":"1000GRKULCEALTIN","buy_price":7956930,"sell_price":8064930,"updated_at":"2026-01-29T07:23:06.529+00:00","name":"1000 Gram Külçe Altın","category":"KULCEALTIN","category_display_name":"Külçe Altın","live_data":false,"icon_path":"icons/gold.png","ui_color":"text-amber-500","ui_bg":"bg-amber-500/20","prefix":"Adet"},{"id":30,"asset_code":"2.5GRKULCEGUMUS","buy_price":420.8,"sell_price":456.02,"updated_at":"2026-01-29T07:23:06.529+00:00","name":"2.5 Gram Külçe Gümüş","category":"KULCEGUMUS","category_display_name":"Külçe Gümüş","live_data":false,"icon_path":"icons/silver.png","ui_color":"text-slate-400","ui_bg":"bg-slate-400/20","prefix":"Adet"},{"id":31,"asset_code":"5GRKULCEGUMUS","buy_price":841.6,"sell_price":912.05,"updated_at":"2026-01-29T07:23:06.529+00:00","name":"5 Gram Külçe Gümüş","category":"KULCEGUMUS","category_display_name":"Külçe Gümüş","live_data":false,"icon_path":"icons/silver.png","ui_color":"text-slate-400","ui_bg":"bg-slate-400/20","prefix":"Adet"},{"id":32,"asset_code":"10GRKULCEGUMUS","buy_price":1683.2,"sell_price":1824.1,"updated_at":"2026-01-29T07:23:06.529+00:00","name":"10 Gram Külçe Gümüş","category":"KULCEGUMUS","category_display_name":"Külçe Gümüş","live_data":false,"icon_path":"icons/silver.png","ui_color":"text-slate-400","ui_bg":"bg-slate-400/20","prefix":"Adet"},{"id":33,"asset_code":"15GRKULCEGUMUS","buy_price":2524.8,"sell_price":2736.15,"updated_at":"2026-01-29T07:23:06.529+00:00","name":"15 Gram Külçe Gümüş","category":"KULCEGUMUS","category_display_name":"Külçe Gümüş","live_data":false,"icon_path":"icons/silver.png","ui_color":"text-slate-400","ui_bg":"bg-slate-400/20","prefix":"Adet"},{"id":34,"asset_code":"20GRKULCEGUMUS","buy_price":3366.4,"sell_price":3648.2,"updated_at":"2026-01-29T07:23:06.529+00:00","name":"20 Gram Külçe Gümüş","category":"KULCEGUMUS","category_display_name":"Külçe Gümüş","live_data":false,"icon_path":"icons/silver.png","ui_color":"text-slate-400","ui_bg":"bg-slate-400/20","prefix":"Adet"},{"id":35,"asset_code":"25GRKULCEGUMUS","buy_price":4208,"sell_price":4560.25,"updated_at":"2026-01-29T07:23:06.529+00:00","name":"25 Gram Külçe Gümüş","category":"KULCEGUMUS","category_display_name":"Külçe Gümüş","live_data":false,"icon_path":"icons/silver.png","ui_color":"text-slate-400","ui_bg":"bg-slate-400/20","prefix":"Adet"},{"id":36,"asset_code":"50GRKULCEGUMUS","buy_price":8416,"sell_price":9120.5,"updated_at":"2026-01-29T07:23:06.529+00:00","name":"50 Gram Külçe Gümüş","category":"KULCEGUMUS","category_display_name":"Külçe Gümüş","live_data":false,"icon_path":"icons/silver.png","ui_color":"text-slate-400","ui_bg":"bg-slate-400/20","prefix":"Adet"},{"id":37,"asset_code":"100GRKULCEGUMUS","buy_price":16832,"sell_price":18241,"updated_at":"2026-01-29T07:23:06.529+00:00","name":"100 Gram Külçe Gümüş","category":"KULCEGUMUS","category_display_name":"Külçe Gümüş","live_data":false,"icon_path":"icons/silver.png","ui_color":"text-slate-400","ui_bg":"bg-slate-400/20","prefix":"Adet"},{"id":38,"asset_code":"200GRKULCEGUMUS","buy_price":33664,"sell_price":36482,"updated_at":"2026-01-29T07:23:06.529+00:00","name":"200 Gram Külçe Gümüş","category":"KULCEGUMUS","category_display_name":"Külçe Gümüş","live_data":false,"icon_path":"icons/silver.png","ui_color":"text-slate-400","ui_bg":"bg-slate-400/20","prefix":"Adet"},{"id":39,"asset_code":"250GRKULCEGUMUS","buy_price":42080,"sell_price":45602.5,"updated_at":"2026-01-29T07:23:06.529+00:00","name":"250 Gram Külçe Gümüş","category":"KULCEGUMUS","category_display_name":"Külçe Gümüş","live_data":false,"icon_path":"icons/silver.png","ui_color":"text-slate-400","ui_bg":"bg-slate-400/20","prefix":"Adet"},{"id":40,"asset_code":"500GRKULCEGUMUS","buy_price":84160,"sell_price":91205,"updated_at":"2026-01-29T07:23:06.529+00:00","name":"500 Gram Külçe Gümüş","category":"KULCEGUMUS","category_display_name":"Külçe Gümüş","live_data":false,"icon_path":"icons/silver.png","ui_color":"text-slate-400","ui_bg":"bg-slate-400/20","prefix":"Adet"},{"id":41,"asset_code":"1000GRKULCEGUMUS","buy_price":168320,"sell_price":182410,"updated_at":"2026-01-29T07:23:06.529+00:00","name":"1000 Gram Külçe Gümüş","category":"KULCEGUMUS","category_display_name":"Külçe Gümüş","live_data":false,"icon_path":"icons/silver.png","ui_color":"text-slate-400","ui_bg":"bg-slate-400/20","prefix":"Adet"},{"id":95,"asset_code":"KRIPTO_BTC","buy_price":3830201,"sell_price":3830202,"updated_at":"2026-01-29T07:23:01.969+00:00","name":"Bitcoin","category":"KRIPTO","category_display_name":"Kripto","live_data":true,"icon_path":"icons/bitcoin.png","ui_color":"text-amber-500","ui_bg":"bg-amber-500/20","prefix":"Adet"},{"id":96,"asset_code":"KRIPTO_ETH","buy_price":128259,"sell_price":128260,"updated_at":"2026-01-29T07:23:01.97+00:00","name":"Ethereum","category":"KRIPTO","category_display_name":"Kripto","live_data":true,"icon_path":"icons/ethereum.png","ui_color":"bg-blue-500","ui_bg":"bg-blue-500/20","prefix":"Adet"},{"id":55,"asset_code":"AKBANK_GA","buy_price":7464.11,"sell_price":7946.14,"updated_at":"2026-01-29T07:23:01.971+00:00","name":"Akbank Gram Altın","category":"BANKAALTIN","category_display_name":"Banka Altın","live_data":true,"icon_path":"icons/gold.png","ui_color":"text-amber-500","ui_bg":"bg-amber-500/20","prefix":"Gram"},{"id":56,"asset_code":"ALBARAKA_GA","buy_price":7634.94,"sell_price":7837.43,"updated_at":"2026-01-29T07:23:01.971+00:00","name":"Albaraka Türk Gram Altın","category":"BANKAALTIN","category_display_name":"Banka Altın","live_data":true,"icon_path":"icons/gold.png","ui_color":"text-amber-500","ui_bg":"bg-amber-500/20","prefix":"Gram"},{"id":57,"asset_code":"ALTERNATIF_GA","buy_price":7615.71,"sell_price":7912.75,"updated_at":"2026-01-29T07:23:01.971+00:00","name":"Alternatif Bank Gram Altın","category":"BANKAALTIN","category_display_name":"Banka Altın","live_data":true,"icon_path":"icons/gold.png","ui_color":"text-amber-500","ui_bg":"bg-amber-500/20","prefix":"Gram"},{"id":58,"asset_code":"ANADOLUBANK_GA","buy_price":7632.5,"sell_price":7792.51,"updated_at":"2026-01-29T07:23:01.971+00:00","name":"Anadolubank Gram Altın","category":"BANKAALTIN","category_display_name":"Banka Altın","live_data":true,"icon_path":"icons/gold.png","ui_color":"text-amber-500","ui_bg":"bg-amber-500/20","prefix":"Gram"},{"id":59,"asset_code":"CEBTETEB_GA","buy_price":7688.62,"sell_price":7824.28,"updated_at":"2026-01-29T07:23:01.971+00:00","name":"CEPTETEB Gram Altın","category":"BANKAALTIN","category_display_name":"Banka Altın","live_data":true,"icon_path":"icons/gold.png","ui_color":"text-amber-500","ui_bg":"bg-amber-500/20","prefix":"Gram"},{"id":60,"asset_code":"DENIZBANK_GA","buy_price":7629.7,"sell_price":7881.82,"updated_at":"2026-01-29T07:23:01.971+00:00","name":"DenizBank Gram Altın","category":"BANKAALTIN","category_display_name":"Banka Altın","live_data":true,"icon_path":"icons/gold.png","ui_color":"text-amber-500","ui_bg":"bg-amber-500/20","prefix":"Gram"},{"id":61,"asset_code":"ENPARA_GA","buy_price":7682.79,"sell_price":7875.92,"updated_at":"2026-01-29T07:23:01.971+00:00","name":"Enpara Gram Altın","category":"BANKAALTIN","category_display_name":"Banka Altın","live_data":true,"icon_path":"icons/gold.png","ui_color":"text-amber-500","ui_bg":"bg-amber-500/20","prefix":"Gram"},{"id":62,"asset_code":"FIBABANKA_GA","buy_price":7727.25,"sell_price":7782.9,"updated_at":"2026-01-29T07:23:01.971+00:00","name":"Fibabanka Gram Altın","category":"BANKAALTIN","category_display_name":"Banka Altın","live_data":true,"icon_path":"icons/gold.png","ui_color":"text-amber-500","ui_bg":"bg-amber-500/20","prefix":"Gram"},{"id":63,"asset_code":"GARANTI_GA","buy_price":7630.97,"sell_price":7850.53,"updated_at":"2026-01-29T07:23:01.971+00:00","name":"Garanti BBVA Gram Altın","category":"BANKAALTIN","category_display_name":"Banka Altın","live_data":true,"icon_path":"icons/gold.png","ui_color":"text-amber-500","ui_bg":"bg-amber-500/20","prefix":"Gram"},{"id":64,"asset_code":"HALKBANK_GA","buy_price":7642.97,"sell_price":7844.52,"updated_at":"2026-01-29T07:23:01.971+00:00","name":"Halkbank Gram Altın","category":"BANKAALTIN","category_display_name":"Banka Altın","live_data":true,"icon_path":"icons/gold.png","ui_color":"text-amber-500","ui_bg":"bg-amber-500/20","prefix":"Gram"},{"id":65,"asset_code":"HSBC_GA","buy_price":7675.85,"sell_price":7794.11,"updated_at":"2026-01-29T07:23:01.971+00:00","name":"HSBC Gram Altın","category":"BANKAALTIN","category_display_name":"Banka Altın","live_data":true,"icon_path":"icons/gold.png","ui_color":"text-amber-500","ui_bg":"bg-amber-500/20","prefix":"Gram"},{"id":66,"asset_code":"ING_GA","buy_price":7690.48,"sell_price":7843.49,"updated_at":"2026-01-29T07:23:01.971+00:00","name":"ING Bank Gram Altın","category":"BANKAALTIN","category_display_name":"Banka Altın","live_data":true,"icon_path":"icons/gold.png","ui_color":"text-amber-500","ui_bg":"bg-amber-500/20","prefix":"Gram"},{"id":67,"asset_code":"KUVEYTTURK_GA","buy_price":7647.57,"sell_price":7850.84,"updated_at":"2026-01-29T07:23:01.971+00:00","name":"Kuveyt Türk Gram Altın","category":"BANKAALTIN","category_display_name":"Banka Altın","live_data":true,"icon_path":"icons/gold.png","ui_color":"text-amber-500","ui_bg":"bg-amber-500/20","prefix":"Gram"},{"id":68,"asset_code":"QNBFB_GA","buy_price":7570.08,"sell_price":7886.34,"updated_at":"2026-01-29T07:23:01.971+00:00","name":"QNB Finansbank Gram Altın","category":"BANKAALTIN","category_display_name":"Banka Altın","live_data":true,"icon_path":"icons/gold.png","ui_color":"text-amber-500","ui_bg":"bg-amber-500/20","prefix":"Gram"},{"id":69,"asset_code":"SEKERBANK_GA","buy_price":7679.41,"sell_price":7768.1,"updated_at":"2026-01-29T07:23:01.971+00:00","name":"Şekerbank Gram Altın","category":"BANKAALTIN","category_display_name":"Banka Altın","live_data":true,"icon_path":"icons/gold.png","ui_color":"text-amber-500","ui_bg":"bg-amber-500/20","prefix":"Gram"},{"id":70,"asset_code":"TURKIYEFINANS_GA","buy_price":7638.97,"sell_price":7836.38,"updated_at":"2026-01-29T07:23:01.971+00:00","name":"Türkiye Finans Gram Altın","category":"BANKAALTIN","category_display_name":"Banka Altın","live_data":true,"icon_path":"icons/gold.png","ui_color":"text-amber-500","ui_bg":"bg-amber-500/20","prefix":"Gram"},{"id":71,"asset_code":"VAKIFBANK_GA","buy_price":7667.7,"sell_price":7812.3,"updated_at":"2026-01-29T07:23:01.971+00:00","name":"VakıfBank Gram Altın","category":"BANKAALTIN","category_display_name":"Banka Altın","live_data":true,"icon_path":"icons/gold.png","ui_color":"text-amber-500","ui_bg":"bg-amber-500/20","prefix":"Gram"},{"id":72,"asset_code":"VAKIFKATILIM_GA","buy_price":7658.72,"sell_price":7769.22,"updated_at":"2026-01-29T07:23:01.971+00:00","name":"Vakıf Katılım Gram Altın","category":"BANKAALTIN","category_display_name":"Banka Altın","live_data":true,"icon_path":"icons/gold.png","ui_color":"text-amber-500","ui_bg":"bg-amber-500/20","prefix":"Gram"},{"id":73,"asset_code":"YAPIKREDI_GA","buy_price":7682.12,"sell_price":7825.46,"updated_at":"2026-01-29T07:23:01.971+00:00","name":"Yapı Kredi Gram Altın","category":"BANKAALTIN","category_display_name":"Banka Altın","live_data":true,"icon_path":"icons/gold.png","ui_color":"text-amber-500","ui_bg":"bg-amber-500/20","prefix":"Gram"},{"id":74,"asset_code":"ZIRAAT_GA","buy_price":7694.84,"sell_price":7896.8,"updated_at":"2026-01-29T07:23:01.971+00:00","name":"Ziraat Bankası Gram Altın","category":"BANKAALTIN","category_display_name":"Banka Altın","live_data":true,"icon_path":"icons/gold.png","ui_color":"text-amber-500","ui_bg":"bg-amber-500/20","prefix":"Gram"},{"id":75,"asset_code":"ZIRAATKATILIM_GA","buy_price":7699.06,"sell_price":7943.6,"updated_at":"2026-01-29T07:23:01.971+00:00","name":"Ziraat Katılım Gram Altın","category":"BANKAALTIN","category_display_name":"Banka Altın","live_data":true,"icon_path":"icons/gold.png","ui_color":"text-amber-500","ui_bg":"bg-amber-500/20","prefix":"Gram"},{"id":42,"asset_code":"HAS_GA","buy_price":7956.93,"sell_price":8064.93,"updated_at":"2026-01-29T07:23:01.971+00:00","name":"Gram Külçe Altın","category":"KULCEALTIN","category_display_name":"Külçe Altın","live_data":true,"icon_path":"icons/gold.png","ui_color":"text-amber-500","ui_bg":"bg-amber-500/20","prefix":"Adet"},{"id":43,"asset_code":"CEYREK_YENI","buy_price":12996,"sell_price":13112,"updated_at":"2026-01-29T07:23:01.971+00:00","name":"Çeyrek Altın","category":"ZIYNET","category_display_name":"Ziynet","live_data":true,"icon_path":"icons/ceyrek_yarim_tam_ata.png","ui_color":"text-amber-500","ui_bg":"bg-amber-500/20","prefix":"Adet"},{"id":44,"asset_code":"CEYREK_ESKI","buy_price":12797,"sell_price":12912,"updated_at":"2026-01-29T07:23:01.971+00:00","name":"Çeyrek Altın Eski","category":"ZIYNET","category_display_name":"Ziynet","live_data":true,"icon_path":"icons/ceyrek_yarim_tam_ata.png","ui_color":"text-amber-500","ui_bg":"bg-amber-500/20","prefix":"Adet"},{"id":45,"asset_code":"YARIM_YENI","buy_price":25992,"sell_price":26225,"updated_at":"2026-01-29T07:23:01.971+00:00","name":"Yarım Altın","category":"ZIYNET","category_display_name":"Ziynet","live_data":true,"icon_path":"icons/ceyrek_yarim_tam_ata.png","ui_color":"text-amber-500","ui_bg":"bg-amber-500/20","prefix":"Adet"},{"id":46,"asset_code":"YARIM_ESKI","buy_price":25514,"sell_price":25720,"updated_at":"2026-01-29T07:23:01.971+00:00","name":"Yarım Altın Eski","category":"ZIYNET","category_display_name":"Ziynet","live_data":true,"icon_path":"icons/ceyrek_yarim_tam_ata.png","ui_color":"text-amber-500","ui_bg":"bg-amber-500/20","prefix":"Adet"},{"id":47,"asset_code":"TAM_YENI","buy_price":51824,"sell_price":52249,"updated_at":"2026-01-29T07:23:01.971+00:00","name":"Tam Altın","category":"ZIYNET","category_display_name":"Ziynet","live_data":true,"icon_path":"icons/ceyrek_yarim_tam_ata.png","ui_color":"text-amber-500","ui_bg":"bg-amber-500/20","prefix":"Adet"},{"id":48,"asset_code":"TAM_ESKI","buy_price":51147,"sell_price":51552,"updated_at":"2026-01-29T07:23:01.971+00:00","name":"Tam Altın Eski","category":"ZIYNET","category_display_name":"Ziynet","live_data":true,"icon_path":"icons/ceyrek_yarim_tam_ata.png","ui_color":"text-amber-500","ui_bg":"bg-amber-500/20","prefix":"Adet"},{"id":49,"asset_code":"ATA_YENI","buy_price":53220,"sell_price":53612,"updated_at":"2026-01-29T07:23:01.971+00:00","name":"Ata Altın","category":"ZIYNET","category_display_name":"Ziynet","live_data":true,"icon_path":"icons/ceyrek_yarim_tam_ata.png","ui_color":"text-amber-500","ui_bg":"bg-amber-500/20","prefix":"Adet"},{"id":50,"asset_code":"ATA_ESKI","buy_price":53220,"sell_price":53612,"updated_at":"2026-01-29T07:23:01.971+00:00","name":"Ata Altın Eski","category":"ZIYNET","category_display_name":"Ziynet","live_data":true,"icon_path":"icons/ceyrek_yarim_tam_ata.png","ui_color":"text-amber-500","ui_bg":"bg-amber-500/20","prefix":"Adet"},{"id":51,"asset_code":"AYAR14","buy_price":4404.87,"sell_price":5710.89,"updated_at":"2026-01-29T07:23:01.971+00:00","name":"14 Ayar","category":"14AYAR","category_display_name":"14 Ayar","live_data":true,"icon_path":"icons/ring.png","ui_color":"text-amber-500","ui_bg":"bg-amber-500/20","prefix":"Adet"},{"id":52,"asset_code":"AYAR22","buy_price":7253.42,"sell_price":7595.92,"updated_at":"2026-01-29T07:23:01.971+00:00","name":"22 Ayar","category":"22AYAR","category_display_name":"22 Ayar","live_data":true,"icon_path":"icons/ring.png","ui_color":"text-amber-500","ui_bg":"bg-amber-500/20","prefix":"Adet"},{"id":53,"asset_code":"HAS_GG","buy_price":168.32,"sell_price":182.41,"updated_at":"2026-01-29T07:23:01.971+00:00","name":"Gram Külçe Gümüş","category":"KULCEGUMUS","category_display_name":"Külçe Gümüş","live_data":true,"icon_path":"icons/silver.png","ui_color":"text-slate-400","ui_bg":"bg-slate-400/20","prefix":"Adet"},{"id":77,"asset_code":"ISBANK_GA","buy_price":7660.17,"sell_price":7824.71,"updated_at":"2026-01-29T07:23:06.562+00:00","name":"İş Bankası Gram Altın","category":"BANKAALTIN","category_display_name":"Banka Altın","live_data":true,"icon_path":"icons/gold.png","ui_color":"text-amber-500","ui_bg":"bg-amber-500/20","prefix":"Gram"},{"id":78,"asset_code":"AKBANK_GG","buy_price":159.98,"sell_price":170.37,"updated_at":"2026-01-29T07:23:09.917+00:00","name":"Akbank Gram Gümüş","category":"BANKAGUMUS","category_display_name":"Banka Gümüş","live_data":true,"icon_path":"icons/silver.png","ui_color":"text-slate-400","ui_bg":"bg-slate-400/20","prefix":"Gram"},{"id":79,"asset_code":"ALBARAKA_GG","buy_price":162.36,"sell_price":168.51,"updated_at":"2026-01-29T07:23:09.917+00:00","name":"Albaraka Türk Gram Gümüş","category":"BANKAGUMUS","category_display_name":"Banka Gümüş","live_data":true,"icon_path":"icons/silver.png","ui_color":"text-slate-400","ui_bg":"bg-slate-400/20","prefix":"Gram"},{"id":80,"asset_code":"ANADOLUBANK_GG","buy_price":163.4,"sell_price":167.53,"updated_at":"2026-01-29T07:23:09.917+00:00","name":"Anadolubank Gram Gümüş","category":"BANKAGUMUS","category_display_name":"Banka Gümüş","live_data":true,"icon_path":"icons/silver.png","ui_color":"text-slate-400","ui_bg":"bg-slate-400/20","prefix":"Gram"},{"id":81,"asset_code":"DENIZBANK_GG","buy_price":162.84,"sell_price":168.25,"updated_at":"2026-01-29T07:23:09.917+00:00","name":"DenizBank Gram Gümüş","category":"BANKAGUMUS","category_display_name":"Banka Gümüş","live_data":true,"icon_path":"icons/silver.png","ui_color":"text-slate-400","ui_bg":"bg-slate-400/20","prefix":"Gram"},{"id":82,"asset_code":"FIBABANKA_GG","buy_price":165.2,"sell_price":166.06,"updated_at":"2026-01-29T07:23:09.917+00:00","name":"Fibabanka Gram Gümüş","category":"BANKAGUMUS","category_display_name":"Banka Gümüş","live_data":true,"icon_path":"icons/silver.png","ui_color":"text-slate-400","ui_bg":"bg-slate-400/20","prefix":"Gram"},{"id":83,"asset_code":"GARANTI_GG","buy_price":163.36,"sell_price":168.04,"updated_at":"2026-01-29T07:23:09.917+00:00","name":"Garanti BBVA Gram Gümüş","category":"BANKAGUMUS","category_display_name":"Banka Gümüş","live_data":true,"icon_path":"icons/silver.png","ui_color":"text-slate-400","ui_bg":"bg-slate-400/20","prefix":"Gram"},{"id":84,"asset_code":"HSBC_GG","buy_price":164.36,"sell_price":167.17,"updated_at":"2026-01-29T07:23:09.917+00:00","name":"HSBC Gram Gümüş","category":"BANKAGUMUS","category_display_name":"Banka Gümüş","live_data":true,"icon_path":"icons/silver.png","ui_color":"text-slate-400","ui_bg":"bg-slate-400/20","prefix":"Gram"},{"id":85,"asset_code":"KUVEYTTURK_GG","buy_price":164.03,"sell_price":168.41,"updated_at":"2026-01-29T07:23:09.917+00:00","name":"Kuveyt Türk Gram Gümüş","category":"BANKAGUMUS","category_display_name":"Banka Gümüş","live_data":true,"icon_path":"icons/silver.png","ui_color":"text-slate-400","ui_bg":"bg-slate-400/20","prefix":"Gram"},{"id":86,"asset_code":"TURKIYEFINANS_GG","buy_price":164.32,"sell_price":170.36,"updated_at":"2026-01-29T07:23:09.917+00:00","name":"Türkiye Finans Gram Gümüş","category":"BANKAGUMUS","category_display_name":"Banka Gümüş","live_data":true,"icon_path":"icons/silver.png","ui_color":"text-slate-400","ui_bg":"bg-slate-400/20","prefix":"Gram"},{"id":87,"asset_code":"VAKIFBANK_GG","buy_price":164.71,"sell_price":166.51,"updated_at":"2026-01-29T07:23:09.917+00:00","name":"VakıfBank Gram Gümüş","category":"BANKAGUMUS","category_display_name":"Banka Gümüş","live_data":true,"icon_path":"icons/silver.png","ui_color":"text-slate-400","ui_bg":"bg-slate-400/20","prefix":"Gram"},{"id":88,"asset_code":"VAKIFKATILIM_GG","buy_price":164.52,"sell_price":166.18,"updated_at":"2026-01-29T07:23:09.917+00:00","name":"Vakıf Katılım Gram Gümüş","category":"BANKAGUMUS","category_display_name":"Banka Gümüş","live_data":true,"icon_path":"icons/silver.png","ui_color":"text-slate-400","ui_bg":"bg-slate-400/20","prefix":"Gram"},{"id":89,"asset_code":"YAPIKREDI_GG","buy_price":163.56,"sell_price":168.68,"updated_at":"2026-01-29T07:23:09.917+00:00","name":"Yapı Kredi Gram Gümüş","category":"BANKAGUMUS","category_display_name":"Banka Gümüş","live_data":true,"icon_path":"icons/silver.png","ui_color":"text-slate-400","ui_bg":"bg-slate-400/20","prefix":"Gram"},{"id":90,"asset_code":"ZIRAATKATILIM_GG","buy_price":164.32,"sell_price":169.91,"updated_at":"2026-01-29T07:23:09.917+00:00","name":"Ziraat Katılım Gram Gümüş","category":"BANKAGUMUS","category_display_name":"Banka Gümüş","live_data":true,"icon_path":"icons/silver.png","ui_color":"text-slate-400","ui_bg":"bg-slate-400/20","prefix":"Gram"},{"id":92,"asset_code":"DOVIZ_DOLAR","buy_price":43.4202,"sell_price":43.4259,"updated_at":"2026-01-29T07:23:10.284+00:00","name":"Dolar","category":"DOVIZ","category_display_name":"Doviz","live_data":true,"icon_path":"icons/dollar-symbol.png","ui_color":"bg-green-400","ui_bg":"bg-green-400/20","prefix":""},{"id":93,"asset_code":"DOVIZ_EURO","buy_price":52.1571,"sell_price":52.1689,"updated_at":"2026-01-29T07:23:10.284+00:00","name":"Euro","category":"DOVIZ","category_display_name":"Doviz","live_data":true,"icon_path":"icons/euro.png","ui_color":"bg-yellow-400","ui_bg":"bg-yellow-400/20","prefix":""},{"id":76,"asset_code":"DOVIZ_STERLIN","buy_price":60.21,"sell_price":60.2497,"updated_at":"2026-01-29T07:23:10.284+00:00","name":"Sterlin","category":"DOVIZ","category_display_name":"Doviz","live_data":true,"icon_path":"icons/pound-sign.png","ui_color":"text-blue-400","ui_bg":"bg-blue-400/20","prefix":""}]