[{"id":1,"asset_code":"5GR22AYARBILEZIK","buy_price":34417.5,"sell_price":35961.55,"updated_at":"2026-01-28T11:15:25.152+00:00","name":"5 Gr 22 Ayar Bilezik","category":"22AYAR","category_display_name":"22 Ayar","live_data":false,"icon_path":"icons/ring.png","ui_color":"text-amber-500","ui_bg":"bg-amber-500/20","prefix":"Adet"},{"id":2,"asset_code":"7GR22AYARBILEZIK","buy_price":48184.5,"sell_price":50346.17,"updated_at":"2026-01-28T11:15:25.152+00:00","name":"7 Gr 22 Ayar Bilezik","category":"22AYAR","category_display_name":"22 Ayar","live_data":false,"icon_path":"icons/ring.png","ui_color":"text-amber-500","ui_bg":"bg-amber-500/20","prefix":"Adet"},{"id":3,"asset_code":"10GR22AYARBILEZIK","buy_price":68835,"sell_price":71923.1,"updated_at":"2026-01-28T11:15:25.152+00:00","name":"10 Gr 22 Ayar Bilezik","category":"22AYAR","category_display_name":"22 Ayar","live_data":false,"icon_path":"icons/ring.png","ui_color":"text-amber-500","ui_bg":"bg-amber-500/20","prefix":"Adet"},{"id":4,"asset_code":"15GR22AYARBILEZIK","buy_price":103252.5,"sell_price":107884.65,"updated_at":"2026-01-28T11:15:25.152+00:00","name":"15 Gr 22 Ayar Bilezik","category":"22AYAR","category_display_name":"22 Ayar","live_data":false,"icon_path":"icons/ring.png","ui_color":"text-amber-500","ui_bg":"bg-amber-500/20","prefix":"Adet"},{"id":5,"asset_code":"20GR22AYARBILEZIK","buy_price":137670,"sell_price":143846.2,"updated_at":"2026-01-28T11:15:25.152+00:00","name":"20 Gr 22 Ayar Bilezik","category":"22AYAR","category_display_name":"22 Ayar","live_data":false,"icon_path":"icons/ring.png","ui_color":"text-amber-500","ui_bg":"bg-amber-500/20","prefix":"Adet"},{"id":6,"asset_code":"25GR22AYARBILEZIK","buy_price":172087.5,"sell_price":179807.75,"updated_at":"2026-01-28T11:15:25.152+00:00","name":"25 Gr 22 Ayar Bilezik","category":"22AYAR","category_display_name":"22 Ayar","live_data":false,"icon_path":"icons/ring.png","ui_color":"text-amber-500","ui_bg":"bg-amber-500/20","prefix":"Adet"},{"id":7,"asset_code":"30GR22AYARBILEZIK","buy_price":206505,"sell_price":215769.3,"updated_at":"2026-01-28T11:15:25.152+00:00","name":"30 Gr 22 Ayar Bilezik","category":"22AYAR","category_display_name":"22 Ayar","live_data":false,"icon_path":"icons/ring.png","ui_color":"text-amber-500","ui_bg":"bg-amber-500/20","prefix":"Adet"},{"id":8,"asset_code":"5GR14AYARBILEZIK","buy_price":20886.15,"sell_price":27173.65,"updated_at":"2026-01-28T11:15:25.152+00:00","name":"5 Gr 14 Ayar Bilezik","category":"14AYAR","category_display_name":"14 Ayar","live_data":false,"icon_path":"icons/ring.png","ui_color":"text-amber-500","ui_bg":"bg-amber-500/20","prefix":"Adet"},{"id":9,"asset_code":"7GR14AYARBILEZIK","buy_price":29240.61,"sell_price":38043.11,"updated_at":"2026-01-28T11:15:25.152+00:00","name":"7 Gr 14 Ayar Bilezik","category":"14AYAR","category_display_name":"14 Ayar","live_data":false,"icon_path":"icons/ring.png","ui_color":"text-amber-500","ui_bg":"bg-amber-500/20","prefix":"Adet"},{"id":10,"asset_code":"10GR14AYARBILEZIK","buy_price":41772.3,"sell_price":54347.3,"updated_at":"2026-01-28T11:15:25.152+00:00","name":"10 Gr 14 Ayar Bilezik","category":"14AYAR","category_display_name":"14 Ayar","live_data":false,"icon_path":"icons/ring.png","ui_color":"text-amber-500","ui_bg":"bg-amber-500/20","prefix":"Adet"},{"id":14,"asset_code":"15GR14AYARBILEZIK","buy_price":62658.45,"sell_price":81520.95,"updated_at":"2026-01-28T11:15:25.152+00:00","name":"15 Gr 14 Ayar Bilezik","category":"14AYAR","category_display_name":"14 Ayar","live_data":false,"icon_path":"icons/ring.png","ui_color":"text-amber-500","ui_bg":"bg-amber-500/20","prefix":"Adet"},{"id":15,"asset_code":"20GR14AYARBILEZIK","buy_price":83544.6,"sell_price":108694.6,"updated_at":"2026-01-28T11:15:25.152+00:00","name":"20 Gr 14 Ayar Bilezik","category":"14AYAR","category_display_name":"14 Ayar","live_data":false,"icon_path":"icons/ring.png","ui_color":"text-amber-500","ui_bg":"bg-amber-500/20","prefix":"Adet"},{"id":16,"asset_code":"25GR14AYARBILEZIK","buy_price":104430.75,"sell_price":135868.25,"updated_at":"2026-01-28T11:15:25.152+00:00","name":"25 Gr 14 Ayar Bilezik","category":"14AYAR","category_display_name":"14 Ayar","live_data":false,"icon_path":"icons/ring.png","ui_color":"text-amber-500","ui_bg":"bg-amber-500/20","prefix":"Adet"},{"id":17,"asset_code":"30GR14AYARBILEZIK","buy_price":125316.9,"sell_price":163041.9,"updated_at":"2026-01-28T11:15:25.152+00:00","name":"30 Gr 14 Ayar Bilezik","category":"14AYAR","category_display_name":"14 Ayar","live_data":false,"icon_path":"icons/ring.png","ui_color":"text-amber-500","ui_bg":"bg-amber-500/20","prefix":"Adet"},{"id":18,"asset_code":"2.5GRKULCEALTIN","buy_price":18878.1,"sell_price":19093.8,"updated_at":"2026-01-28T11:15:25.152+00:00","name":"2.5 Gram Külçe Altın","category":"KULCEALTIN","category_display_name":"Külçe Altın","live_data":false,"icon_path":"icons/gold.png","ui_color":"text-amber-500","ui_bg":"bg-amber-500/20","prefix":"Adet"},{"id":19,"asset_code":"5GRKULCEALTIN","buy_price":37756.2,"sell_price":38187.6,"updated_at":"2026-01-28T11:15:25.152+00:00","name":"5 Gram Külçe Altın","category":"KULCEALTIN","category_display_name":"Külçe Altın","live_data":false,"icon_path":"icons/gold.png","ui_color":"text-amber-500","ui_bg":"bg-amber-500/20","prefix":"Adet"},{"id":20,"asset_code":"10GRKULCEALTIN","buy_price":75512.4,"sell_price":76375.2,"updated_at":"2026-01-28T11:15:25.152+00:00","name":"10 Gram Külçe Altın","category":"KULCEALTIN","category_display_name":"Külçe Altın","live_data":false,"icon_path":"icons/gold.png","ui_color":"text-amber-500","ui_bg":"bg-amber-500/20","prefix":"Adet"},{"id":21,"asset_code":"15GRKULCEALTIN","buy_price":113268.6,"sell_price":114562.8,"updated_at":"2026-01-28T11:15:25.152+00:00","name":"15 Gram Külçe Altın","category":"KULCEALTIN","category_display_name":"Külçe Altın","live_data":false,"icon_path":"icons/gold.png","ui_color":"text-amber-500","ui_bg":"bg-amber-500/20","prefix":"Adet"},{"id":22,"asset_code":"20GRKULCEALTIN","buy_price":151024.8,"sell_price":152750.4,"updated_at":"2026-01-28T11:15:25.152+00:00","name":"20 Gram Külçe Altın","category":"KULCEALTIN","category_display_name":"Külçe Altın","live_data":false,"icon_path":"icons/gold.png","ui_color":"text-amber-500","ui_bg":"bg-amber-500/20","prefix":"Adet"},{"id":23,"asset_code":"25GRKULCEALTIN","buy_price":188781,"sell_price":190938,"updated_at":"2026-01-28T11:15:25.152+00:00","name":"25 Gram Külçe Altın","category":"KULCEALTIN","category_display_name":"Külçe Altın","live_data":false,"icon_path":"icons/gold.png","ui_color":"text-amber-500","ui_bg":"bg-amber-500/20","prefix":"Adet"},{"id":24,"asset_code":"50GRKULCEALTIN","buy_price":377562,"sell_price":381876,"updated_at":"2026-01-28T11:15:25.152+00:00","name":"50 Gram Külçe Altın","category":"KULCEALTIN","category_display_name":"Külçe Altın","live_data":false,"icon_path":"icons/gold.png","ui_color":"text-amber-500","ui_bg":"bg-amber-500/20","prefix":"Adet"},{"id":25,"asset_code":"100GRKULCEALTIN","buy_price":755124,"sell_price":763752,"updated_at":"2026-01-28T11:15:25.152+00:00","name":"100 Gram Külçe Altın","category":"KULCEALTIN","category_display_name":"Külçe Altın","live_data":false,"icon_path":"icons/gold.png","ui_color":"text-amber-500","ui_bg":"bg-amber-500/20","prefix":"Adet"},{"id":26,"asset_code":"200GRKULCEALTIN","buy_price":1510248,"sell_price":1527504,"updated_at":"2026-01-28T11:15:25.152+00:00","name":"200 Gram Külçe Altın","category":"KULCEALTIN","category_display_name":"Külçe Altın","live_data":false,"icon_path":"icons/gold.png","ui_color":"text-amber-500","ui_bg":"bg-amber-500/20","prefix":"Adet"},{"id":27,"asset_code":"250GRKULCEALTIN","buy_price":1887810,"sell_price":1909380,"updated_at":"2026-01-28T11:15:25.152+00:00","name":"250 Gram Külçe Altın","category":"KULCEALTIN","category_display_name":"Külçe Altın","live_data":false,"icon_path":"icons/gold.png","ui_color":"text-amber-500","ui_bg":"bg-amber-500/20","prefix":"Adet"},{"id":28,"asset_code":"500GRKULCEALTIN","buy_price":3775620,"sell_price":3818760,"updated_at":"2026-01-28T11:15:25.152+00:00","name":"500 Gram Külçe Altın","category":"KULCEALTIN","category_display_name":"Külçe Altın","live_data":false,"icon_path":"icons/gold.png","ui_color":"text-amber-500","ui_bg":"bg-amber-500/20","prefix":"Adet"},{"id":29,"asset_code":"1000GRKULCEALTIN","buy_price":7551240,"sell_price":7637520,"updated_at":"2026-01-28T11:15:25.152+00:00","name":"1000 Gram Külçe Altın","category":"KULCEALTIN","category_display_name":"Külçe Altın","live_data":false,"icon_path":"icons/gold.png","ui_color":"text-amber-500","ui_bg":"bg-amber-500/20","prefix":"Adet"},{"id":30,"asset_code":"2.5GRKULCEGUMUS","buy_price":397.3,"sell_price":432.15,"updated_at":"2026-01-28T11:15:25.152+00:00","name":"2.5 Gram Külçe Gümüş","category":"KULCEGUMUS","category_display_name":"Külçe Gümüş","live_data":false,"icon_path":"icons/silver.png","ui_color":"text-slate-400","ui_bg":"bg-slate-400/20","prefix":"Adet"},{"id":31,"asset_code":"5GRKULCEGUMUS","buy_price":794.6,"sell_price":864.3,"updated_at":"2026-01-28T11:15:25.152+00:00","name":"5 Gram Külçe Gümüş","category":"KULCEGUMUS","category_display_name":"Külçe Gümüş","live_data":false,"icon_path":"icons/silver.png","ui_color":"text-slate-400","ui_bg":"bg-slate-400/20","prefix":"Adet"},{"id":32,"asset_code":"10GRKULCEGUMUS","buy_price":1589.2,"sell_price":1728.6,"updated_at":"2026-01-28T11:15:25.152+00:00","name":"10 Gram Külçe Gümüş","category":"KULCEGUMUS","category_display_name":"Külçe Gümüş","live_data":false,"icon_path":"icons/silver.png","ui_color":"text-slate-400","ui_bg":"bg-slate-400/20","prefix":"Adet"},{"id":33,"asset_code":"15GRKULCEGUMUS","buy_price":2383.8,"sell_price":2592.9,"updated_at":"2026-01-28T11:15:25.152+00:00","name":"15 Gram Külçe Gümüş","category":"KULCEGUMUS","category_display_name":"Külçe Gümüş","live_data":false,"icon_path":"icons/silver.png","ui_color":"text-slate-400","ui_bg":"bg-slate-400/20","prefix":"Adet"},{"id":34,"asset_code":"20GRKULCEGUMUS","buy_price":3178.4,"sell_price":3457.2,"updated_at":"2026-01-28T11:15:25.152+00:00","name":"20 Gram Külçe Gümüş","category":"KULCEGUMUS","category_display_name":"Külçe Gümüş","live_data":false,"icon_path":"icons/silver.png","ui_color":"text-slate-400","ui_bg":"bg-slate-400/20","prefix":"Adet"},{"id":35,"asset_code":"25GRKULCEGUMUS","buy_price":3973,"sell_price":4321.5,"updated_at":"2026-01-28T11:15:25.152+00:00","name":"25 Gram Külçe Gümüş","category":"KULCEGUMUS","category_display_name":"Külçe Gümüş","live_data":false,"icon_path":"icons/silver.png","ui_color":"text-slate-400","ui_bg":"bg-slate-400/20","prefix":"Adet"},{"id":36,"asset_code":"50GRKULCEGUMUS","buy_price":7946,"sell_price":8643,"updated_at":"2026-01-28T11:15:25.152+00:00","name":"50 Gram Külçe Gümüş","category":"KULCEGUMUS","category_display_name":"Külçe Gümüş","live_data":false,"icon_path":"icons/silver.png","ui_color":"text-slate-400","ui_bg":"bg-slate-400/20","prefix":"Adet"},{"id":37,"asset_code":"100GRKULCEGUMUS","buy_price":15892,"sell_price":17286,"updated_at":"2026-01-28T11:15:25.152+00:00","name":"100 Gram Külçe Gümüş","category":"KULCEGUMUS","category_display_name":"Külçe Gümüş","live_data":false,"icon_path":"icons/silver.png","ui_color":"text-slate-400","ui_bg":"bg-slate-400/20","prefix":"Adet"},{"id":38,"asset_code":"200GRKULCEGUMUS","buy_price":31784,"sell_price":34572,"updated_at":"2026-01-28T11:15:25.152+00:00","name":"200 Gram Külçe Gümüş","category":"KULCEGUMUS","category_display_name":"Külçe Gümüş","live_data":false,"icon_path":"icons/silver.png","ui_color":"text-slate-400","ui_bg":"bg-slate-400/20","prefix":"Adet"},{"id":39,"asset_code":"250GRKULCEGUMUS","buy_price":39730,"sell_price":43215,"updated_at":"2026-01-28T11:15:25.152+00:00","name":"250 Gram Külçe Gümüş","category":"KULCEGUMUS","category_display_name":"Külçe Gümüş","live_data":false,"icon_path":"icons/silver.png","ui_color":"text-slate-400","ui_bg":"bg-slate-400/20","prefix":"Adet"},{"id":40,"asset_code":"500GRKULCEGUMUS","buy_price":79460,"sell_price":86430,"updated_at":"2026-01-28T11:15:25.152+00:00","name":"500 Gram Külçe Gümüş","category":"KULCEGUMUS","category_display_name":"Külçe Gümüş","live_data":false,"icon_path":"icons/silver.png","ui_color":"text-slate-400","ui_bg":"bg-slate-400/20","prefix":"Adet"},{"id":41,"asset_code":"1000GRKULCEGUMUS","buy_price":158920,"sell_price":172860,"updated_at":"2026-01-28T11:15:25.152+00:00","name":"1000 Gram Külçe Gümüş","category":"KULCEGUMUS","category_display_name":"Külçe Gümüş","live_data":false,"icon_path":"icons/silver.png","ui_color":"text-slate-400","ui_bg":"bg-slate-400/20","prefix":"Adet"},{"id":95,"asset_code":"KRIPTO_BTC","buy_price":3869668,"sell_price":3869669,"updated_at":"2026-01-28T11:15:20.398+00:00","name":"Bitcoin","category":"KRIPTO","category_display_name":"Kripto","live_data":true,"icon_path":"icons/bitcoin.png","ui_color":"text-amber-500","ui_bg":"bg-amber-500/20","prefix":"Adet"},{"id":96,"asset_code":"KRIPTO_ETH","buy_price":130716,"sell_price":130717,"updated_at":"2026-01-28T11:15:20.398+00:00","name":"Ethereum","category":"KRIPTO","category_display_name":"Kripto","live_data":true,"icon_path":"icons/ethereum.png","ui_color":"bg-blue-500","ui_bg":"bg-blue-500/20","prefix":"Adet"},{"id":55,"asset_code":"AKBANK_GA","buy_price":7056.76,"sell_price":7512.67,"updated_at":"2026-01-28T11:15:20.399+00:00","name":"Akbank Gram Altın","category":"BANKAALTIN","category_display_name":"Banka Altın","live_data":true,"icon_path":"icons/gold.png","ui_color":"text-amber-500","ui_bg":"bg-amber-500/20","prefix":"Gram"},{"id":56,"asset_code":"ALBARAKA_GA","buy_price":7218.48,"sell_price":7407.78,"updated_at":"2026-01-28T11:15:20.399+00:00","name":"Albaraka Türk Gram Altın","category":"BANKAALTIN","category_display_name":"Banka Altın","live_data":true,"icon_path":"icons/gold.png","ui_color":"text-amber-500","ui_bg":"bg-amber-500/20","prefix":"Gram"},{"id":57,"asset_code":"ALTERNATIF_GA","buy_price":7268.45,"sell_price":7406.41,"updated_at":"2026-01-28T11:15:20.399+00:00","name":"Alternatif Bank Gram Altın","category":"BANKAALTIN","category_display_name":"Banka Altın","live_data":true,"icon_path":"icons/gold.png","ui_color":"text-amber-500","ui_bg":"bg-amber-500/20","prefix":"Gram"},{"id":58,"asset_code":"ANADOLUBANK_GA","buy_price":7215.46,"sell_price":7368.49,"updated_at":"2026-01-28T11:15:20.399+00:00","name":"Anadolubank Gram Altın","category":"BANKAALTIN","category_display_name":"Banka Altın","live_data":true,"icon_path":"icons/gold.png","ui_color":"text-amber-500","ui_bg":"bg-amber-500/20","prefix":"Gram"},{"id":59,"asset_code":"CEBTETEB_GA","buy_price":7263.96,"sell_price":7399.75,"updated_at":"2026-01-28T11:15:20.399+00:00","name":"CEPTETEB Gram Altın","category":"BANKAALTIN","category_display_name":"Banka Altın","live_data":true,"icon_path":"icons/gold.png","ui_color":"text-amber-500","ui_bg":"bg-amber-500/20","prefix":"Gram"},{"id":60,"asset_code":"DENIZBANK_GA","buy_price":7211.49,"sell_price":7449.65,"updated_at":"2026-01-28T11:15:20.399+00:00","name":"DenizBank Gram Altın","category":"BANKAALTIN","category_display_name":"Banka Altın","live_data":true,"icon_path":"icons/gold.png","ui_color":"text-amber-500","ui_bg":"bg-amber-500/20","prefix":"Gram"},{"id":61,"asset_code":"ENPARA_GA","buy_price":7235.93,"sell_price":7388.46,"updated_at":"2026-01-28T11:15:20.399+00:00","name":"Enpara Gram Altın","category":"BANKAALTIN","category_display_name":"Banka Altın","live_data":true,"icon_path":"icons/gold.png","ui_color":"text-amber-500","ui_bg":"bg-amber-500/20","prefix":"Gram"},{"id":62,"asset_code":"FIBABANKA_GA","buy_price":7305.82,"sell_price":7360.91,"updated_at":"2026-01-28T11:15:20.399+00:00","name":"Fibabanka Gram Altın","category":"BANKAALTIN","category_display_name":"Banka Altın","live_data":true,"icon_path":"icons/gold.png","ui_color":"text-amber-500","ui_bg":"bg-amber-500/20","prefix":"Gram"},{"id":63,"asset_code":"GARANTI_GA","buy_price":7220.38,"sell_price":7428.14,"updated_at":"2026-01-28T11:15:20.399+00:00","name":"Garanti BBVA Gram Altın","category":"BANKAALTIN","category_display_name":"Banka Altın","live_data":true,"icon_path":"icons/gold.png","ui_color":"text-amber-500","ui_bg":"bg-amber-500/20","prefix":"Gram"},{"id":64,"asset_code":"HALKBANK_GA","buy_price":7233.63,"sell_price":7413.86,"updated_at":"2026-01-28T11:15:20.399+00:00","name":"Halkbank Gram Altın","category":"BANKAALTIN","category_display_name":"Banka Altın","live_data":true,"icon_path":"icons/gold.png","ui_color":"text-amber-500","ui_bg":"bg-amber-500/20","prefix":"Gram"},{"id":65,"asset_code":"HSBC_GA","buy_price":7253.85,"sell_price":7370.3,"updated_at":"2026-01-28T11:15:20.399+00:00","name":"HSBC Gram Altın","category":"BANKAALTIN","category_display_name":"Banka Altın","live_data":true,"icon_path":"icons/gold.png","ui_color":"text-amber-500","ui_bg":"bg-amber-500/20","prefix":"Gram"},{"id":66,"asset_code":"ING_GA","buy_price":7260.62,"sell_price":7413.13,"updated_at":"2026-01-28T11:15:20.399+00:00","name":"ING Bank Gram Altın","category":"BANKAALTIN","category_display_name":"Banka Altın","live_data":true,"icon_path":"icons/gold.png","ui_color":"text-amber-500","ui_bg":"bg-amber-500/20","prefix":"Gram"},{"id":67,"asset_code":"KUVEYTTURK_GA","buy_price":7228.58,"sell_price":7419.17,"updated_at":"2026-01-28T11:15:20.399+00:00","name":"Kuveyt Türk Gram Altın","category":"BANKAALTIN","category_display_name":"Banka Altın","live_data":true,"icon_path":"icons/gold.png","ui_color":"text-amber-500","ui_bg":"bg-amber-500/20","prefix":"Gram"},{"id":68,"asset_code":"QNBFB_GA","buy_price":7147.56,"sell_price":7416.61,"updated_at":"2026-01-28T11:15:20.4+00:00","name":"QNB Finansbank Gram Altın","category":"BANKAALTIN","category_display_name":"Banka Altın","live_data":true,"icon_path":"icons/gold.png","ui_color":"text-amber-500","ui_bg":"bg-amber-500/20","prefix":"Gram"},{"id":69,"asset_code":"SEKERBANK_GA","buy_price":7258.32,"sell_price":7342.92,"updated_at":"2026-01-28T11:15:20.4+00:00","name":"Şekerbank Gram Altın","category":"BANKAALTIN","category_display_name":"Banka Altın","live_data":true,"icon_path":"icons/gold.png","ui_color":"text-amber-500","ui_bg":"bg-amber-500/20","prefix":"Gram"},{"id":70,"asset_code":"TURKIYEFINANS_GA","buy_price":7220.23,"sell_price":7416.82,"updated_at":"2026-01-28T11:15:20.4+00:00","name":"Türkiye Finans Gram Altın","category":"BANKAALTIN","category_display_name":"Banka Altın","live_data":true,"icon_path":"icons/gold.png","ui_color":"text-amber-500","ui_bg":"bg-amber-500/20","prefix":"Gram"},{"id":71,"asset_code":"VAKIFBANK_GA","buy_price":7250.58,"sell_price":7395.18,"updated_at":"2026-01-28T11:15:20.4+00:00","name":"VakıfBank Gram Altın","category":"BANKAALTIN","category_display_name":"Banka Altın","live_data":true,"icon_path":"icons/gold.png","ui_color":"text-amber-500","ui_bg":"bg-amber-500/20","prefix":"Gram"},{"id":72,"asset_code":"VAKIFKATILIM_GA","buy_price":7237.11,"sell_price":7341.52,"updated_at":"2026-01-28T11:15:20.4+00:00","name":"Vakıf Katılım Gram Altın","category":"BANKAALTIN","category_display_name":"Banka Altın","live_data":true,"icon_path":"icons/gold.png","ui_color":"text-amber-500","ui_bg":"bg-amber-500/20","prefix":"Gram"},{"id":73,"asset_code":"YAPIKREDI_GA","buy_price":7256,"sell_price":7395.68,"updated_at":"2026-01-28T11:15:20.4+00:00","name":"Yapı Kredi Gram Altın","category":"BANKAALTIN","category_display_name":"Banka Altın","live_data":true,"icon_path":"icons/gold.png","ui_color":"text-amber-500","ui_bg":"bg-amber-500/20","prefix":"Gram"},{"id":74,"asset_code":"ZIRAAT_GA","buy_price":7257.37,"sell_price":7447.84,"updated_at":"2026-01-28T11:15:20.4+00:00","name":"Ziraat Bankası Gram Altın","category":"BANKAALTIN","category_display_name":"Banka Altın","live_data":true,"icon_path":"icons/gold.png","ui_color":"text-amber-500","ui_bg":"bg-amber-500/20","prefix":"Gram"},{"id":75,"asset_code":"ZIRAATKATILIM_GA","buy_price":7277.92,"sell_price":7508.3,"updated_at":"2026-01-28T11:15:20.4+00:00","name":"Ziraat Katılım Gram Altın","category":"BANKAALTIN","category_display_name":"Banka Altın","live_data":true,"icon_path":"icons/gold.png","ui_color":"text-amber-500","ui_bg":"bg-amber-500/20","prefix":"Gram"},{"id":42,"asset_code":"HAS_GA","buy_price":7551.24,"sell_price":7637.52,"updated_at":"2026-01-28T11:15:20.4+00:00","name":"Gram Külçe Altın","category":"KULCEALTIN","category_display_name":"Külçe Altın","live_data":true,"icon_path":"icons/gold.png","ui_color":"text-amber-500","ui_bg":"bg-amber-500/20","prefix":"Adet"},{"id":43,"asset_code":"CEYREK_YENI","buy_price":12333,"sell_price":12418,"updated_at":"2026-01-28T11:15:20.4+00:00","name":"Çeyrek Altın","category":"ZIYNET","category_display_name":"Ziynet","live_data":true,"icon_path":"icons/ceyrek_yarim_tam_ata.png","ui_color":"text-amber-500","ui_bg":"bg-amber-500/20","prefix":"Adet"},{"id":44,"asset_code":"CEYREK_ESKI","buy_price":12144,"sell_price":12228,"updated_at":"2026-01-28T11:15:20.4+00:00","name":"Çeyrek Altın Eski","category":"ZIYNET","category_display_name":"Ziynet","live_data":true,"icon_path":"icons/ceyrek_yarim_tam_ata.png","ui_color":"text-amber-500","ui_bg":"bg-amber-500/20","prefix":"Adet"},{"id":45,"asset_code":"YARIM_YENI","buy_price":24667,"sell_price":24836,"updated_at":"2026-01-28T11:15:20.4+00:00","name":"Yarım Altın","category":"ZIYNET","category_display_name":"Ziynet","live_data":true,"icon_path":"icons/ceyrek_yarim_tam_ata.png","ui_color":"text-amber-500","ui_bg":"bg-amber-500/20","prefix":"Adet"},{"id":46,"asset_code":"YARIM_ESKI","buy_price":24213,"sell_price":24357,"updated_at":"2026-01-28T11:15:20.4+00:00","name":"Yarım Altın Eski","category":"ZIYNET","category_display_name":"Ziynet","live_data":true,"icon_path":"icons/ceyrek_yarim_tam_ata.png","ui_color":"text-amber-500","ui_bg":"bg-amber-500/20","prefix":"Adet"},{"id":47,"asset_code":"TAM_YENI","buy_price":49182,"sell_price":49481,"updated_at":"2026-01-28T11:15:20.4+00:00","name":"Tam Altın","category":"ZIYNET","category_display_name":"Ziynet","live_data":true,"icon_path":"icons/ceyrek_yarim_tam_ata.png","ui_color":"text-amber-500","ui_bg":"bg-amber-500/20","prefix":"Adet"},{"id":48,"asset_code":"TAM_ESKI","buy_price":48539,"sell_price":48821,"updated_at":"2026-01-28T11:15:20.4+00:00","name":"Tam Altın Eski","category":"ZIYNET","category_display_name":"Ziynet","live_data":true,"icon_path":"icons/ceyrek_yarim_tam_ata.png","ui_color":"text-amber-500","ui_bg":"bg-amber-500/20","prefix":"Adet"},{"id":49,"asset_code":"ATA_YENI","buy_price":50506,"sell_price":50772,"updated_at":"2026-01-28T11:15:20.4+00:00","name":"Ata Altın","category":"ZIYNET","category_display_name":"Ziynet","live_data":true,"icon_path":"icons/ceyrek_yarim_tam_ata.png","ui_color":"text-amber-500","ui_bg":"bg-amber-500/20","prefix":"Adet"},{"id":50,"asset_code":"ATA_ESKI","buy_price":50506,"sell_price":50772,"updated_at":"2026-01-28T11:15:20.4+00:00","name":"Ata Altın Eski","category":"ZIYNET","category_display_name":"Ziynet","live_data":true,"icon_path":"icons/ceyrek_yarim_tam_ata.png","ui_color":"text-amber-500","ui_bg":"bg-amber-500/20","prefix":"Adet"},{"id":51,"asset_code":"AYAR14","buy_price":4177.23,"sell_price":5434.73,"updated_at":"2026-01-28T11:15:20.4+00:00","name":"14 Ayar","category":"14AYAR","category_display_name":"14 Ayar","live_data":true,"icon_path":"icons/ring.png","ui_color":"text-amber-500","ui_bg":"bg-amber-500/20","prefix":"Adet"},{"id":52,"asset_code":"AYAR22","buy_price":6883.5,"sell_price":7192.31,"updated_at":"2026-01-28T11:15:20.4+00:00","name":"22 Ayar","category":"22AYAR","category_display_name":"22 Ayar","live_data":true,"icon_path":"icons/ring.png","ui_color":"text-amber-500","ui_bg":"bg-amber-500/20","prefix":"Adet"},{"id":53,"asset_code":"HAS_GG","buy_price":158.92,"sell_price":172.86,"updated_at":"2026-01-28T11:15:20.4+00:00","name":"Gram Külçe Gümüş","category":"KULCEGUMUS","category_display_name":"Külçe Gümüş","live_data":true,"icon_path":"icons/silver.png","ui_color":"text-slate-400","ui_bg":"bg-slate-400/20","prefix":"Adet"},{"id":77,"asset_code":"ISBANK_GA","buy_price":7238.46,"sell_price":7394.73,"updated_at":"2026-01-28T11:15:25.182+00:00","name":"İş Bankası Gram Altın","category":"BANKAALTIN","category_display_name":"Banka Altın","live_data":true,"icon_path":"icons/gold.png","ui_color":"text-amber-500","ui_bg":"bg-amber-500/20","prefix":"Gram"},{"id":78,"asset_code":"AKBANK_GG","buy_price":150.79,"sell_price":160.62,"updated_at":"2026-01-28T11:15:34.508+00:00","name":"Akbank Gram Gümüş","category":"BANKAGUMUS","category_display_name":"Banka Gümüş","live_data":true,"icon_path":"icons/silver.png","ui_color":"text-slate-400","ui_bg":"bg-slate-400/20","prefix":"Gram"},{"id":79,"asset_code":"ALBARAKA_GG","buy_price":153.08,"sell_price":158.89,"updated_at":"2026-01-28T11:15:34.508+00:00","name":"Albaraka Türk Gram Gümüş","category":"BANKAGUMUS","category_display_name":"Banka Gümüş","live_data":true,"icon_path":"icons/silver.png","ui_color":"text-slate-400","ui_bg":"bg-slate-400/20","prefix":"Gram"},{"id":80,"asset_code":"ANADOLUBANK_GG","buy_price":153.71,"sell_price":157.6,"updated_at":"2026-01-28T11:15:34.508+00:00","name":"Anadolubank Gram Gümüş","category":"BANKAGUMUS","category_display_name":"Banka Gümüş","live_data":true,"icon_path":"icons/silver.png","ui_color":"text-slate-400","ui_bg":"bg-slate-400/20","prefix":"Gram"},{"id":81,"asset_code":"DENIZBANK_GG","buy_price":153.35,"sell_price":158.48,"updated_at":"2026-01-28T11:15:34.508+00:00","name":"DenizBank Gram Gümüş","category":"BANKAGUMUS","category_display_name":"Banka Gümüş","live_data":true,"icon_path":"icons/silver.png","ui_color":"text-slate-400","ui_bg":"bg-slate-400/20","prefix":"Gram"},{"id":82,"asset_code":"FIBABANKA_GG","buy_price":155.78,"sell_price":156.63,"updated_at":"2026-01-28T11:15:34.508+00:00","name":"Fibabanka Gram Gümüş","category":"BANKAGUMUS","category_display_name":"Banka Gümüş","live_data":true,"icon_path":"icons/silver.png","ui_color":"text-slate-400","ui_bg":"bg-slate-400/20","prefix":"Gram"},{"id":83,"asset_code":"GARANTI_GG","buy_price":154.21,"sell_price":158.62,"updated_at":"2026-01-28T11:15:34.508+00:00","name":"Garanti BBVA Gram Gümüş","category":"BANKAGUMUS","category_display_name":"Banka Gümüş","live_data":true,"icon_path":"icons/silver.png","ui_color":"text-slate-400","ui_bg":"bg-slate-400/20","prefix":"Gram"},{"id":84,"asset_code":"HSBC_GG","buy_price":154.45,"sell_price":157.26,"updated_at":"2026-01-28T11:15:34.508+00:00","name":"HSBC Gram Gümüş","category":"BANKAGUMUS","category_display_name":"Banka Gümüş","live_data":true,"icon_path":"icons/silver.png","ui_color":"text-slate-400","ui_bg":"bg-slate-400/20","prefix":"Gram"},{"id":85,"asset_code":"KUVEYTTURK_GG","buy_price":154.21,"sell_price":158.31,"updated_at":"2026-01-28T11:15:34.508+00:00","name":"Kuveyt Türk Gram Gümüş","category":"BANKAGUMUS","category_display_name":"Banka Gümüş","live_data":true,"icon_path":"icons/silver.png","ui_color":"text-slate-400","ui_bg":"bg-slate-400/20","prefix":"Gram"},{"id":86,"asset_code":"TURKIYEFINANS_GG","buy_price":154.92,"sell_price":160.98,"updated_at":"2026-01-28T11:15:34.508+00:00","name":"Türkiye Finans Gram Gümüş","category":"BANKAGUMUS","category_display_name":"Banka Gümüş","live_data":true,"icon_path":"icons/silver.png","ui_color":"text-slate-400","ui_bg":"bg-slate-400/20","prefix":"Gram"},{"id":87,"asset_code":"VAKIFBANK_GG","buy_price":155.14,"sell_price":156.93,"updated_at":"2026-01-28T11:15:34.508+00:00","name":"VakıfBank Gram Gümüş","category":"BANKAGUMUS","category_display_name":"Banka Gümüş","live_data":true,"icon_path":"icons/silver.png","ui_color":"text-slate-400","ui_bg":"bg-slate-400/20","prefix":"Gram"},{"id":88,"asset_code":"VAKIFKATILIM_GG","buy_price":154.86,"sell_price":156.42,"updated_at":"2026-01-28T11:15:34.508+00:00","name":"Vakıf Katılım Gram Gümüş","category":"BANKAGUMUS","category_display_name":"Banka Gümüş","live_data":true,"icon_path":"icons/silver.png","ui_color":"text-slate-400","ui_bg":"bg-slate-400/20","prefix":"Gram"},{"id":89,"asset_code":"YAPIKREDI_GG","buy_price":153.27,"sell_price":158.99,"updated_at":"2026-01-28T11:15:34.508+00:00","name":"Yapı Kredi Gram Gümüş","category":"BANKAGUMUS","category_display_name":"Banka Gümüş","live_data":true,"icon_path":"icons/silver.png","ui_color":"text-slate-400","ui_bg":"bg-slate-400/20","prefix":"Gram"},{"id":90,"asset_code":"ZIRAATKATILIM_GG","buy_price":154.55,"sell_price":159.82,"updated_at":"2026-01-28T11:15:34.508+00:00","name":"Ziraat Katılım Gram Gümüş","category":"BANKAGUMUS","category_display_name":"Banka Gümüş","live_data":true,"icon_path":"icons/silver.png","ui_color":"text-slate-400","ui_bg":"bg-slate-400/20","prefix":"Gram"},{"id":92,"asset_code":"DOVIZ_DOLAR","buy_price":43.409,"sell_price":43.4189,"updated_at":"2026-01-28T11:15:40.838+00:00","name":"Dolar","category":"DOVIZ","category_display_name":"Doviz","live_data":true,"icon_path":"icons/dollar-symbol.png","ui_color":"bg-green-400","ui_bg":"bg-green-400/20","prefix":""},{"id":93,"asset_code":"DOVIZ_EURO","buy_price":52.0168,"sell_price":52.0262,"updated_at":"2026-01-28T11:15:40.838+00:00","name":"Euro","category":"DOVIZ","category_display_name":"Doviz","live_data":true,"icon_path":"icons/euro.png","ui_color":"bg-yellow-400","ui_bg":"bg-yellow-400/20","prefix":""},{"id":76,"asset_code":"DOVIZ_STERLIN","buy_price":59.8408,"sell_price":59.8544,"updated_at":"2026-01-28T11:15:40.838+00:00","name":"Sterlin","category":"DOVIZ","category_display_name":"Doviz","live_data":true,"icon_path":"icons/pound-sign.png","ui_color":"text-blue-400","ui_bg":"bg-blue-400/20","prefix":""}]